Workbook

Sheet Owners Info
A1: Building | B1: Property | C1: Status | D1: GC Status | E1: Unit Type | F1: Unit Owner (WIP) | G1: Email (WIP) | H1: Contact Number | I1: Classification | J1: Effective Date | K1: Expiry Date | L1: Expiry Tracker | M1: Contract (WIP) | N1: AIRBNB | O1: BOOKING .COM | P1: AGODA | Q1: HOSTEEVA | R1: YOUR RENTALS | S1: TRIP.COM | T1: INVENTORY LIST
A2: Avida Storeys 1 | B2: P S1 503 | C2: ACTIVE | D2: FIXED | E2: 2-Bedroom | F2: Nino Donato Pison | G2: n_pison@yahoo.com | I2: Fixed | J2: 45184 | K2: MISSING | L2: =ifs(C2="INACTIVE","INACTIVE",C2="IN PROGRESS","IN PROGRESS",K2="","",K2="MISSING","?",K2-TODAY()>0,K2-TODAY(),K2-TODAY()<0,"EXPIRED") -> ? | N2: P S1 503 | O2: P Fantastic 2BR Option for 8 | P2: P S1 503
A3: Avida Storeys 1 | B3: S S1 717 | C3: ACTIVE | D3: FIXED | E3: 1-Bedroom | F3: Revrose Selyn Pison | G3: n_pison@yahoo.com | I3: Fixed | J3: 45180 | K3: MISSING | L3: =ifs(C3="INACTIVE","INACTIVE",C3="IN PROGRESS","IN PROGRESS",K3="","",K3="MISSING","?",K3-TODAY()>0,K3-TODAY(),K3-TODAY()<0,"EXPIRED") -> ? | N3: S S1 717 | O3: S Urban Dreamscape | P3: S S1 717
A4: Avida Storeys 1 | B4: S1 408 | C4: ACTIVE | D4: FIXED | E4: STOCKROOM | F4: Edgardo Pison | G4: n_pison@yahoo.com | I4: Fixed | J4: 45180 | K4: MISSING | L4: =ifs(C4="INACTIVE","INACTIVE",C4="IN PROGRESS","IN PROGRESS",K4="","",K4="MISSING","?",K4-TODAY()>0,K4-TODAY(),K4-TODAY()<0,"EXPIRED") -> ?
A5: Avida Storeys 1 | B5: S2 S1 210 | C5: ACTIVE | D5: FIXED | E5: 1-Bedroom | F5: Dondon Pison | G5: n_pison@yahoo.com | I5: Fixed | J5: 45458 | K5: 46188 | L5: =ifs(C5="INACTIVE","INACTIVE",C5="IN PROGRESS","IN PROGRESS",K5="","",K5="MISSING","?",K5-TODAY()>0,K5-TODAY(),K5-TODAY()<0,"EXPIRED") -> EXPIRED | N5: S2 S1 210 | O5: S2 Chic Minimalist Escape | P5: S2 S1 210
A6: Avida Storeys 1 | B6: H S1 506 | C6: INACTIVE | D6: N/A | E6: 1-Bedroom | F6: Bacolod Concept Realty Corp. | G6: n_pison@yahoo.com | I6: Fixed | J6: 45061 | K6: MISSING | L6: =ifs(C6="INACTIVE","INACTIVE",C6="IN PROGRESS","IN PROGRESS",K6="","",K6="MISSING","?",K6-TODAY()>0,K6-TODAY(),K6-TODAY()<0,"EXPIRED") -> INACTIVE | N6: H S1 506 | O6: H Incomparable Value
A7: Avida Storeys 1 | B7: Y S1 704 | C7: ACTIVE | D7: NOT YET | E7: 2-Bedroom | F7: Goldamier Ybera Chua | G7: goldameirchua@gycmarketingopc.com | I7: Partnership | J7: 45717 | K7: 46082 | L7: =ifs(C7="INACTIVE","INACTIVE",C7="IN PROGRESS","IN PROGRESS",K7="","",K7="MISSING","?",K7-TODAY()>0,K7-TODAY(),K7-TODAY()<0,"EXPIRED") -> EXPIRED | N7: Y S1 704 | O7: Y Stylish 2BR Option for up to 6 | P7: Y S1 704
A8: Avida Storeys 2 | B8: Y2 S2 203 | C8: ACTIVE | D8: MESSENGER | E8: 1-Bedroom | F8: Ma. Crislyne Mae Espinosa | G8: arlandbarvilla@gmail.com | I8: Partnership | J8: 45506 | K8: 45871 | L8: =ifs(C8="INACTIVE","INACTIVE",C8="IN PROGRESS","IN PROGRESS",K8="","",K8="MISSING","?",K8-TODAY()>0,K8-TODAY(),K8-TODAY()<0,"EXPIRED") -> EXPIRED | M8: Y2 S2 203 - ESPINOSA.pdf | N8: Y2 S2 203 | O8: Y2 Pool & Garden Bliss | P8: Y2 S2 203
A9: Avida Storeys 2 | B9: K2 S2 322 | C9: ACTIVE | D9: FIXED | E9: 1-Bedroom | G9: n_pison@yahoo.com | I9: Fixed | J9: 45245 | K9: MISSING | L9: =ifs(C9="INACTIVE","INACTIVE",C9="IN PROGRESS","IN PROGRESS",K9="","",K9="MISSING","?",K9-TODAY()>0,K9-TODAY(),K9-TODAY()<0,"EXPIRED") -> ? | N9: K2 S2 322 | O9: K2 Nordic Haven | P9: K2 S2 322
A10: Avida Storeys 2 | B10: L S2 716 | C10: ACTIVE | D10: FIXED | E10: 1-Bedroom | F10: Raymund Trenas | G10: raytrenas@gmail.com | I10: Fixed | J10: 45180 | K10: MISSING | L10: =ifs(C10="INACTIVE","INACTIVE",C10="IN PROGRESS","IN PROGRESS",K10="","",K10="MISSING","?",K10-TODAY()>0,K10-TODAY(),K10-TODAY()<0,"EXPIRED") -> ? | N10: L S2 716 | O10: L Iloilo's Quirky Oasis
A11: Avida Storeys 2 | B11: T2 S2 703 | C11: FOR RENEWAL | D11: NOT YET | E11: 1-Bedroom | F11: Leo Paranpan | G11: lparanpan@yahoo.com | H11: (+63) 917 127 3533 | I11: Partnership | J11: 45461 | K11: 45826 | L11: =ifs(C11="INACTIVE","INACTIVE",C11="IN PROGRESS","IN PROGRESS",K11="","",K11="MISSING","?",K11-TODAY()>0,K11-TODAY(),K11-TODAY()<0,"EXPIRED") -> EXPIRED | M11: T2 S2 703 - PARANPAN.pdf | N11: T2 S2 703 | O11: T2 Serene Pool View Escape | P11: T2 S2 703
A12: Avida Tower 1 | B12: D T1 917 | C12: ACTIVE | D12: MESSENGER | E12: Studio | F12: Robert Stanley Po | G12: cltpo@icloud.com | H12: (+63) 917 844 3012 | I12: Partnership | J12: 45809 | K12: 46174 | L12: =ifs(C12="INACTIVE","INACTIVE",C12="IN PROGRESS","IN PROGRESS",K12="","",K12="MISSING","?",K12-TODAY()>0,K12-TODAY(),K12-TODAY()<0,"EXPIRED") -> EXPIRED | N12: D T1 917 | O12: D Peaceful and Comfortable Room | P12: D T1 917
A13: Avida Tower 1 | B13: C3 T1 428 | C13: ACTIVE | D13: MESSENGER | E13: 2-Bedroom | F13: Ramona Beck | G13: mona_beck2001@yahoo.com | H13: (+63) 935 489 5373 | I13: 75/25 Partner | J13: 45635 | K13: 46000 | L13: =ifs(C13="INACTIVE","INACTIVE",C13="IN PROGRESS","IN PROGRESS",K13="","",K13="MISSING","?",K13-TODAY()>0,K13-TODAY(),K13-TODAY()<0,"EXPIRED") -> EXPIRED | N13: C3 T1 428 | O13: C3 Elegant 2BR Condo with Pool View | P13: C3 T1 428
A14: Avida Tower 1 | B14: A3 T1 1524 | C14: INACTIVE | D14: N/A | E14: Studio | F14: Elvie Dofitas | G14: Elvie.dofitas08@gmail.com | H14: (+63) 917 680 0008 | I14: 75/25 Partner | J14: 45600 | K14: 45781 | L14: =ifs(C14="INACTIVE","INACTIVE",C14="IN PROGRESS","IN PROGRESS",K14="","",K14="MISSING","?",K14-TODAY()>0,K14-TODAY(),K14-TODAY()<0,"EXPIRED") -> INACTIVE | M14: A3 T1 1524 - DOFITAS.pdf | N14: A3 T1 1524 | O14: A3 Central Studio Getaway | P14: A3 T1 1524
A15: Avida Tower 1 | B15: V2 T1 306 | C15: ACTIVE | D15: NOT YET | E15: Studio | F15: Dondon Pison | G15: n_pison@yahoo.com | I15: Partnership | L15: =ifs(C15="INACTIVE","INACTIVE",C15="IN PROGRESS","IN PROGRESS",K15="","",K15="MISSING","?",K15-TODAY()>0,K15-TODAY(),K15-TODAY()<0,"EXPIRED") | N15: V2 T1 306 | O15: V2 Relaxing Studio Escape | P15: V2 T1 306
A16: Avida Tower 1 | B16: B AT T1 501 | C16: ACTIVE | D16: VIBER | E16: 1-Bedroom | F16: Angelina Cordero / Sarah Angela Cordero | G16: docangie.thesmileologists@gmail.com | H16: (+63) 905 446 6439 | I16: 85/15 Partner | L16: =ifs(C16="INACTIVE","INACTIVE",C16="IN PROGRESS","IN PROGRESS",K16="","",K16="MISSING","?",K16-TODAY()>0,K16-TODAY(),K16-TODAY()<0,"EXPIRED")
A17: Avida Tower 1 | B17: U2 T1 221 | C17: ACTIVE | D17: VIBER | E17: 1-Bedroom | F17: Ira Villanueva Valenzuela | G17: villanueva_ira@yahoo.com | H17: (+63) 917 305 2499 | I17: Partnership | J17: 45474 | K17: 45839 | L17: =ifs(C17="INACTIVE","INACTIVE",C17="IN PROGRESS","IN PROGRESS",K17="","",K17="MISSING","?",K17-TODAY()>0,K17-TODAY(),K17-TODAY()<0,"EXPIRED") -> EXPIRED | M17: U2 T1 221 - VILLANUEVA.pdf | N17: U2 T1 221 | O17: U2 Spacious 1BR Retreat | P17: U2 T1 221
A18: Avida Tower 2 | B18: T T2 815 | C18: ACTIVE | D18: FIXED | E18: Studio | F18: William Del Rosario | G18: bdelrosario1014@gmail.com | I18: Fixed | L18: =ifs(C18="INACTIVE","INACTIVE",C18="IN PROGRESS","IN PROGRESS",K18="","",K18="MISSING","?",K18-TODAY()>0,K18-TODAY(),K18-TODAY()<0,"EXPIRED") | N18: T T2 815 | O18: T Panoramic Metro View | P18: T T2 815
A19: Avida Tower 2 | B19: E2 T2 309 | C19: ACTIVE | D19: FIXED | E19: Studio | F19: Mary Joyce Torrefranca | G19: cant0910@yahoo.com | H19: (+63) 917 319 5794 | I19: Fixed | J19: 45698 | K19: MISSING | L19: =ifs(C19="INACTIVE","INACTIVE",C19="IN PROGRESS","IN PROGRESS",K19="","",K19="MISSING","?",K19-TODAY()>0,K19-TODAY(),K19-TODAY()<0,"EXPIRED") -> ? | N19: E2 T2 309 | O19: E2 Oasis in the City
A20: Avida Tower 2 | B20: R T2 1423 | C20: ACTIVE | D20: FIXED | E20: Studio | F20: Irene Lachica | G20: irene.lachica@yahoo.com | H20: (+63) 923 741 5922 | I20: Fixed | J20: 45184 | K20: MISSING | L20: =ifs(C20="INACTIVE","INACTIVE",C20="IN PROGRESS","IN PROGRESS",K20="","",K20="MISSING","?",K20-TODAY()>0,K20-TODAY(),K20-TODAY()<0,"EXPIRED") -> ? | N20: R T2 1423 | O20: R Metropolitan Mirage | P20: R T2 1423
A21: Avida Tower 2 | B21: I2 T2 522 | C21: ACTIVE | D21: FIXED | E21: Studio | F21: Lourdes Carney | G21: Lourdes.carney@gmail.com | I21: Fixed | J21: 45294 | K21: MISSING | L21: =ifs(C21="INACTIVE","INACTIVE",C21="IN PROGRESS","IN PROGRESS",K21="","",K21="MISSING","?",K21-TODAY()>0,K21-TODAY(),K21-TODAY()<0,"EXPIRED") -> ? | N21: I2 T2 522 | O21: I2 Sleek City Haven | P21: I2 T2 522
A22: Avida Tower 2 | B22: B2 T2 108 | C22: ACTIVE | D22: FIXED | E22: Studio | F22: Edward Espinosa | G22: mariespinosa3185@gmail.com | I22: Fixed | J22: 45294 | K22: MISSING | L22: =ifs(C22="INACTIVE","INACTIVE",C22="IN PROGRESS","IN PROGRESS",K22="","",K22="MISSING","?",K22-TODAY()>0,K22-TODAY(),K22-TODAY()<0,"EXPIRED") -> ? | N22: B2 T2 108 | O22: B2 Your Go-To Crib
A23: Avida Tower 2 | B23: F T2 1020 | C23: ACTIVE | D23: FIXED | E23: Studio | F23: Kathreen Socorro Piamonte | I23: Fixed | J23: 45022 | K23: MISSING | L23: =ifs(C23="INACTIVE","INACTIVE",C23="IN PROGRESS","IN PROGRESS",K23="","",K23="MISSING","?",K23-TODAY()>0,K23-TODAY(),K23-TODAY()<0,"EXPIRED") -> ? | N23: F T2 1020 | O23: F Best Vlaue in Iloilo | P23: F T2 1020
A24: Avida Tower 2 | B24: N T2 421 | C24: ACTIVE | D24: FIXED | E24: Studio | F24: Roberto Gelvezon | I24: Fixed | J24: 45143 | L24: =ifs(C24="INACTIVE","INACTIVE",C24="IN PROGRESS","IN PROGRESS",K24="","",K24="MISSING","?",K24-TODAY()>0,K24-TODAY(),K24-TODAY()<0,"EXPIRED") | N24: N T2 421 | O24: N Affordable Urban Luxury | P24: N T2 421
A25: Avida Tower 2 | B25: Q T2 420 | C25: ACTIVE | D25: FIXED | E25: Studio | F25: Gerard Teofilo Gelvezon | I25: Fixed | J25: 45184 | K25: MISSING | L25: =ifs(C25="INACTIVE","INACTIVE",C25="IN PROGRESS","IN PROGRESS",K25="","",K25="MISSING","?",K25-TODAY()>0,K25-TODAY(),K25-TODAY()<0,"EXPIRED") -> ? | N25: Q T2 420 | O25: Q Incomparable Comfort for 3 | P25: Q T2 420
A26: Avida Tower 2 | B26: X T2 1021 | C26: ACTIVE | D26: FIXED | E26: Studio | F26: Michael Borro | I26: Fixed | J26: 45107 | K26: 46203 | L26: =ifs(C26="INACTIVE","INACTIVE",C26="IN PROGRESS","IN PROGRESS",K26="","",K26="MISSING","?",K26-TODAY()>0,K26-TODAY(),K26-TODAY()<0,"EXPIRED") -> EXPIRED | N26: X T2 1021 | O26: X Metro Bliss
A27: Avida Tower 2 | B27: H2 T2 521 | C27: ACTIVE | D27: FIXED | E27: Studio | F27: Maria Rita Jardiolin | G27: Ritaj241@yahoo.com | I27: Fixed | J27: 45294 | K27: MISSING | L27: =ifs(C27="INACTIVE","INACTIVE",C27="IN PROGRESS","IN PROGRESS",K27="","",K27="MISSING","?",K27-TODAY()>0,K27-TODAY(),K27-TODAY()<0,"EXPIRED") -> ? | N27: H2 T2 521 | O27: H2 Modern City Condo | P27: H2 T2 521
A28: Avida Tower 2 | B28: Q2 T2 1221 | C28: INACTIVE | D28: N/A | E28: Studio | F28: Maria Grace Puertollano | G28: graceuybico@gmail.com | I28: Partnership | L28: =ifs(C28="INACTIVE","INACTIVE",C28="IN PROGRESS","IN PROGRESS",K28="","",K28="MISSING","?",K28-TODAY()>0,K28-TODAY(),K28-TODAY()<0,"EXPIRED") -> INACTIVE | N28: Q2 T2 1221 | O28: Q2 City View Twin Room | P28: Q2 T2 1221
A29: Avida Tower 2 | B29: A T2 322 | C29: ACTIVE | D29: NOT YET | E29: Studio | F29: Aaron James Sales | G29: Aaronsales.j@gmail.com | I29: 85/15 Partner | J29: 45729 | K29: 45821 | L29: =ifs(C29="INACTIVE","INACTIVE",C29="IN PROGRESS","IN PROGRESS",K29="","",K29="MISSING","?",K29-TODAY()>0,K29-TODAY(),K29-TODAY()<0,"EXPIRED") -> EXPIRED | N29: A T2 322 | O29: A Charming Urban Retreat | P29: A T2 322
A30: Avida Tower 2 | B30: # T2 209 | C30: ACTIVE | D30: VIBER | E30: Studio | F30: Fredilyn Samoro/Katrina Samoro | H30: (+63) 0917 701 0178. 0917 893 6246 | I30: 85/15 Partner | J30: 45769 | K30: 45961 | L30: =ifs(C30="INACTIVE","INACTIVE",C30="IN PROGRESS","IN PROGRESS",K30="","",K30="MISSING","?",K30-TODAY()>0,K30-TODAY(),K30-TODAY()<0,"EXPIRED") -> EXPIRED
A31: Avida Tower 3 | B31: D2 T3 626 | C31: ACTIVE | D31: FIXED | E31: Studio | F31: Donnave Caramat | G31: dgcaramat12@gmail.com | I31: Fixed | J31: 45294 | K31: MISSING | L31: =ifs(C31="INACTIVE","INACTIVE",C31="IN PROGRESS","IN PROGRESS",K31="","",K31="MISSING","?",K31-TODAY()>0,K31-TODAY(),K31-TODAY()<0,"EXPIRED") -> ? | N31: D2 T3 626 | O31: D2 Central Location Condo
A32: Avida Tower 2 | B32: # T2 209
A33: Avida Tower 3 | B33: I T3 725 | C33: INACTIVE | D33: N/A | E33: Studio | F33: Mechelle Balasa Rey | G33: jayson12mendoza15@gmail.com | I33: Fixed | J33: 45070 | K33: MISSING | L33: =ifs(C33="INACTIVE","INACTIVE",C33="IN PROGRESS","IN PROGRESS",K33="","",K33="MISSING","?",K33-TODAY()>0,K33-TODAY(),K33-TODAY()<0,"EXPIRED") -> INACTIVE | N33: I T3 725 | O33: I Best Value Studio
A34: Avida Tower 3 | B34: B3 T3 1011 | C34: ACTIVE | D34: NOT YET | E34: Studio | F34: Gutierrez Dev. Company | G34: gutierrezdevelopment@gmail.com | I34: 75/25 Partner | J34: 45611 | K34: MISSING | L34: =ifs(C34="INACTIVE","INACTIVE",C34="IN PROGRESS","IN PROGRESS",K34="","",K34="MISSING","?",K34-TODAY()>0,K34-TODAY(),K34-TODAY()<0,"EXPIRED") -> ? | N34: B3 T3 1011 | O34: B3 Chic Sunset Studio Escape | P34: B3 T3 1011
A35: Avida Tower 3 | B35: W2 T3 207 | C35: ACTIVE | D35: VIBER | E35: Studio | F35: Pancho Bringas / Christine Magallanes | G35: Ceee_m@yahoo.com | H35: (+63) 917 303 1696 | I35: Partnership | J35: 45506 | K35: 45871 | L35: =ifs(C35="INACTIVE","INACTIVE",C35="IN PROGRESS","IN PROGRESS",K35="","",K35="MISSING","?",K35-TODAY()>0,K35-TODAY(),K35-TODAY()<0,"EXPIRED") -> EXPIRED | N35: W2 T3 207 | O35: W2 Cozy Urban Nest | P35: W2 T3 207
A36: Avida Tower 3 | B36: X2 T3 528 | C36: ACTIVE | D36: VIBER | E36: Studio | F36: Pancho Bringas / Christine Magallanes | G36: Ceee_m@yahoo.com | H36: (+63) 917 303 1696 | I36: Partnership | J36: 45506 | K36: 45871 | L36: =ifs(C36="INACTIVE","INACTIVE",C36="IN PROGRESS","IN PROGRESS",K36="","",K36="MISSING","?",K36-TODAY()>0,K36-TODAY(),K36-TODAY()<0,"EXPIRED") -> EXPIRED | N36: X2 T3 528 | O36: X2 Urban Zen Studio | P36: X2 T3 528
A37: Avida Tower 3 | B37: Z2 T3 526 | C37: ACTIVE | D37: VIBER | E37: Studio | F37: Czarina Ngan | G37: e43eee3esdwafcfvfcffvgvgrdcrxseexttfddfddz;;p-p-p= | H37: (+63) 917 701 8684 | I37: 85/15 Partner | J37: 45769 | K37: 45869 | L37: =ifs(C37="INACTIVE","INACTIVE",C37="IN PROGRESS","IN PROGRESS",K37="","",K37="MISSING","?",K37-TODAY()>0,K37-TODAY(),K37-TODAY()<0,"EXPIRED") -> EXPIRED | N37: Z2 T3 526 | O37: Z2 Modern Zen Hideaway | P37: Z2 T3 526
A38: Avida Tower 3 | B38: M2 T3 424 | C38: ACTIVE | D38: VIBER | E38: Studio | F38: Leyson San Juan | G38: leyson37@gmail.com | H38: (+63) 917 713 7994 | I38: Partnership | J38: 45811 | K38: 46176 | L38: =ifs(C38="INACTIVE","INACTIVE",C38="IN PROGRESS","IN PROGRESS",K38="","",K38="MISSING","?",K38-TODAY()>0,K38-TODAY(),K38-TODAY()<0,"EXPIRED") -> EXPIRED | N38: M2 T3 424 | O38: M2 Minimalist and Cozy Studio | P38: M2 T3 424
A39: Avida Tower 3 | B39: N2 T3 426 | C39: ACTIVE | D39: VIBER | E39: Studio | F39: Leyson San Juan | G39: leyson37@gmail.com | H39: (+63) 917 713 7994 | I39: Partnership | J39: 45811 | K39: 46176 | L39: =ifs(C39="INACTIVE","INACTIVE",C39="IN PROGRESS","IN PROGRESS",K39="","",K39="MISSING","?",K39-TODAY()>0,K39-TODAY(),K39-TODAY()<0,"EXPIRED") -> EXPIRED | N39: N2 T3 426 | O39: N2 Sleek Urban Escape | P39: N2 T3 426
A40: Avida Tower 3 | B40: O2 T3 826 | C40: ACTIVE | D40: VIBER | E40: Studio | F40: Leyson San Juan | G40: leyson37@gmail.com | H40: (+63) 917 713 7994 | I40: Partnership | J40: 45811 | K40: 46176 | L40: =ifs(C40="INACTIVE","INACTIVE",C40="IN PROGRESS","IN PROGRESS",K40="","",K40="MISSING","?",K40-TODAY()>0,K40-TODAY(),K40-TODAY()<0,"EXPIRED") -> EXPIRED | M40: AT T3 826 - SAN JUAN (RENEWAL).pdf | N40: O2 T3 826 | O40: O2 Urban Zen Retreat | P40: O2 T3 826
A41: Avida Tower 4 | B41: J2 T4 117 | C41: ACTIVE | D41: MESSENGER | E41: Studio | F41: Cherry Villa / Jeseryl Villa | G41: kixmd@yahoo.com | I41: 85/15 Partner | J41: 45809 | K41: 46174 | L41: =ifs(C41="INACTIVE","INACTIVE",C41="IN PROGRESS","IN PROGRESS",K41="","",K41="MISSING","?",K41-TODAY()>0,K41-TODAY(),K41-TODAY()<0,"EXPIRED") -> EXPIRED | M41: AT T4 117 - PINK/VILLA.pdf
A42: Bernwood Tower | B42: BT 1 1222 | C42: ACTIVE | D42: NOT YET | E42: Studio | F42: Ruth Santisteban Serrato | G42: ruthserrato@yahoo.com | I42: Partnership | J42: 45748 | K42: 45930 | L42: =ifs(C42="INACTIVE","INACTIVE",C42="IN PROGRESS","IN PROGRESS",K42="","",K42="MISSING","?",K42-TODAY()>0,K42-TODAY(),K42-TODAY()<0,"EXPIRED") -> EXPIRED | N42: BT 1 1222 | O42: BT 1 Chic City Studio Retreat | P42: BT 1 1222
A43: Lafayette | B43: 6 LPS 16S | C43: ACTIVE | D43: MESSENGER | E43: Studio | F43: Christine Ladigohon | G43: christineladigohon@gmail.com | H43: (+63) 939 181 8824 | I43: Partnership | J43: 45800 | K43: 46349 | L43: =ifs(C43="INACTIVE","INACTIVE",C43="IN PROGRESS","IN PROGRESS",K43="","",K43="MISSING","?",K43-TODAY()>0,K43-TODAY(),K43-TODAY()<0,"EXPIRED") -> 88 | M43: LPS 16S - LADIGOHON.pdf | N43: 6 LPS 16S | O43: 6 Simple Pearl Retreat | P43: 6 LPS 16S
A44: Lafayette | B44: 42 LPS 5E | C44: ACTIVE | D44: MESSENGER | E44: Executive Studio | F44: Mary Jean Bearneza | G44: cornerhome99@gmail.com | H44: (+63) 919 384 4464 | I44: 85/15 Partner | J44: 45805 | K44: 46170 | L44: =ifs(C44="INACTIVE","INACTIVE",C44="IN PROGRESS","IN PROGRESS",K44="","",K44="MISSING","?",K44-TODAY()>0,K44-TODAY(),K44-TODAY()<0,"EXPIRED") -> EXPIRED | M44: LPS 5E - BEARNEZA.pdf
A45: Lafayette | B45: 25 LPS 8S | C45: ACTIVE | D45: MESSENGER | E45: Studio | F45: Julius Jacomille | G45: rentwithus.abc@gmail.com | H45: (+1) (204) 807 2346 | I45: 75/25 Partner | J45: 45579 | K45: 45944 | L45: =ifs(C45="INACTIVE","INACTIVE",C45="IN PROGRESS","IN PROGRESS",K45="","",K45="MISSING","?",K45-TODAY()>0,K45-TODAY(),K45-TODAY()<0,"EXPIRED") -> EXPIRED | M45: 25 LPS 8S - JACOMILLE.pdf | N45: 25 LPS 8S | O45: 25 Central Luxury Studio | P45: 25 LPS 8S
A46: Lafayette | B46: 18 LPS 9R | C46: ACTIVE | D46: MESSENGER | E46: Studio | F46: Risty Durbin | G46: ristyd@yahoo.com | I46: Partnership | J46: 45531 | K46: 45896 | L46: =ifs(C46="INACTIVE","INACTIVE",C46="IN PROGRESS","IN PROGRESS",K46="","",K46="MISSING","?",K46-TODAY()>0,K46-TODAY(),K46-TODAY()<0,"EXPIRED") -> EXPIRED | M46: 18 LPS 9R - DURBIN.pdf | N46: 18 LPS 9R | O46: 18 Warm Studio Oasis | P46: 18 LPS 9R
A47: Lafayette | B47: 24 LPS 9PQ | C47: ACTIVE | D47: MESSENGER | E47: 1-Bedroom | F47: Risty Durbin | G47: ristyd@yahoo.com | I47: Partnership | J47: 45566 | K47: 45931 | L47: =ifs(C47="INACTIVE","INACTIVE",C47="IN PROGRESS","IN PROGRESS",K47="","",K47="MISSING","?",K47-TODAY()>0,K47-TODAY(),K47-TODAY()<0,"EXPIRED") -> EXPIRED | M47: 24 LPS 9PQ - DURBIN.pdf | N47: 24 LPS 9PQ | O47: 24 Modern 1-Bedroom Minimalist Sanctuary | P47: 24 LPS 9PQ
A48: Lafayette | B48: 22 LPS 8J | C48: ACTIVE | D48: NOT YET | E48: 1-Bedroom | F48: Adonis Zapanta | G48: dimple_email2@yahoo.com | I48: Partnership | J48: 45531 | K48: 45896 | L48: =ifs(C48="INACTIVE","INACTIVE",C48="IN PROGRESS","IN PROGRESS",K48="","",K48="MISSING","?",K48-TODAY()>0,K48-TODAY(),K48-TODAY()<0,"EXPIRED") -> EXPIRED | M48: 22 LPS 8J -ZAPANTA.pdf | N48: 22 LPS 8J | O48: 22 Luxurious 1-Bedroom Apartment | P48: 22 LPS 8J
A49: Lafayette | B49: 34 LPS 5Z | C49: ACTIVE | D49: VIBER | E49: Studio | F49: Maria Emily Belicena | G49: emilybelicena@gmail.com | H49: (+63) 917 317 7203 | I49: Partnership | J49: 45707 | K49: 46010 | L49: =ifs(C49="INACTIVE","INACTIVE",C49="IN PROGRESS","IN PROGRESS",K49="","",K49="MISSING","?",K49-TODAY()>0,K49-TODAY(),K49-TODAY()<0,"EXPIRED") -> EXPIRED | M49: 34 LPS 5Z - BELICENA.pdf | N49: 34 LPS 5Z | O49: 34 Retro Chic Studio | P49: 34 LPS 5Z
A50: Lafayette | B50: 35 LPS 5Y | C50: ACTIVE | D50: VIBER | E50: Studio | F50: Maria Emily Belicena | G50: emilybelicena@gmail.com | H50: (+63) 917 317 7204 | I50: Partnership | J50: 45707 | K50: 46010 | L50: =ifs(C50="INACTIVE","INACTIVE",C50="IN PROGRESS","IN PROGRESS",K50="","",K50="MISSING","?",K50-TODAY()>0,K50-TODAY(),K50-TODAY()<0,"EXPIRED") -> EXPIRED | M50: 35 LPS 5Y - BELICENA.pdf | N50: 35 LPS 5Y | O50: 35 Adorable Studio | P50: 35 LPS 5Y
A51: Lafayette | B51: 5 LPS 16T | C51: ACTIVE | D51: VIBER | E51: Studio | F51: Esther Palmares | G51: Esjoyp@aol.com | H51: (+63) 917 898 9043 | I51: Partnership | J51: 45670 | K51: 46035 | L51: =ifs(C51="INACTIVE","INACTIVE",C51="IN PROGRESS","IN PROGRESS",K51="","",K51="MISSING","?",K51-TODAY()>0,K51-TODAY(),K51-TODAY()<0,"EXPIRED") -> EXPIRED | M51: LPS 16T - PALMARES.pdf | N51: 5 LPS 16T | O51: 5 Modern Chic Studio | P51: 5 LPS 16T
A52: Lafayette | B52: 16 LPS 15X | C52: ACTIVE | D52: VIBER | E52: Studio | F52: Euniel Solinap | G52: euniel.md@gmail.com | I52: Partnership | J52: 45635 | K52: 45874 | L52: =ifs(C52="INACTIVE","INACTIVE",C52="IN PROGRESS","IN PROGRESS",K52="","",K52="MISSING","?",K52-TODAY()>0,K52-TODAY(),K52-TODAY()<0,"EXPIRED") -> EXPIRED | M52: 16 LPS 15X - SOLINAP.pdf | N52: 16 LPS 15X | O52: 16 Cozy and Spacious Studio | P52: 16 LPS 15X
A53: Lafayette | B53: 15 LPS 10-O | C53: ACTIVE | D53: VIBER | E53: 1-Bedroom | F53: Michael Limsiaco | G53: limsiacomichael@yahoo.com | H53: (+63) 918 901 2626 | I53: Partnership | J53: 45503 | K53: 45868 | L53: =ifs(C53="INACTIVE","INACTIVE",C53="IN PROGRESS","IN PROGRESS",K53="","",K53="MISSING","?",K53-TODAY()>0,K53-TODAY(),K53-TODAY()<0,"EXPIRED") -> EXPIRED | M53: 15 LPS 10-O - LIMSIACO.pdf | N53: 15 LPS 10-O | O53: 15 Elegant Urban Suite | P53: 15 LPS 10-O
A54: One Madison | B54: 41 OMP T3 10K | C54: ACTIVE | D54: MESSENGER | E54: Studio | F54: Ibrahim Khalilullah Maricar / Marny Ringo | G54: ibrahimmaricar@outlook.com | H54: (+971) 555 911519 | I54: Partnership | J54: 45778 | K54: 46143 | L54: =ifs(C54="INACTIVE","INACTIVE",C54="IN PROGRESS","IN PROGRESS",K54="","",K54="MISSING","?",K54-TODAY()>0,K54-TODAY(),K54-TODAY()<0,"EXPIRED") -> EXPIRED | M54: OMP T3 10K - MARICAR/RINGO
A55: One Madison | B55: 45 OMP T2 9L | C55: ACTIVE | D55: MESSENGER | E55: Studio | F55: Ross Lim | G55: rosslim07@gmail.com | I55: 85/15 Partner | J55: 45835 | K55: 46199 | L55: =ifs(C55="INACTIVE","INACTIVE",C55="IN PROGRESS","IN PROGRESS",K55="","",K55="MISSING","?",K55-TODAY()>0,K55-TODAY(),K55-TODAY()<0,"EXPIRED") -> EXPIRED | M55: 45 OMP T2 9L.pdf | N55: 45 OMP T2 9L
A56: One Madison | B56: 3 OMP T3 10-O | C56: ACTIVE | D56: NOT YET | E56: Studio | F56: Cynthia Mansueto | G56: cynthiamansueto@yahoo.com.ph | H56: (+63) 926 319 4338 | I56: Partnership | J56: 45624 | K56: 45989 | L56: =ifs(C56="INACTIVE","INACTIVE",C56="IN PROGRESS","IN PROGRESS",K56="","",K56="MISSING","?",K56-TODAY()>0,K56-TODAY(),K56-TODAY()<0,"EXPIRED") -> EXPIRED | N56: 3 OMP T3 10-O | O56: 3 Iloilo's Dream Studio | P56: 3 OMP T3 10-O
A57: One Madison | B57: 32 OMP T3 10E | C57: ACTIVE | D57: NOT YET | E57: Studio | F57: Hyacinth Faraon | G57: Hyacinth.9@hotmail.com | I57: Partnership | J57: 45673 | K57: 46038 | L57: =ifs(C57="INACTIVE","INACTIVE",C57="IN PROGRESS","IN PROGRESS",K57="","",K57="MISSING","?",K57-TODAY()>0,K57-TODAY(),K57-TODAY()<0,"EXPIRED") -> EXPIRED | M57: 32 OMP T3 10E - FARAON.pdf | N57: 32 OMP T3 10E | O57: 32 Best Value Family Suite | P57: 32 OMP T3 10E
A58: One Madison | B58: 2 OMP T1 8D | C58: ACTIVE | D58: VIBER | E58: Studio | F58: Maja Armonio | G58: airbnbaccou@gmail.com | I58: Partnership | J58: 45525 | K58: 45890 | L58: =ifs(C58="INACTIVE","INACTIVE",C58="IN PROGRESS","IN PROGRESS",K58="","",K58="MISSING","?",K58-TODAY()>0,K58-TODAY(),K58-TODAY()<0,"EXPIRED") -> EXPIRED | N58: 2 OMP T1 8D | O58: 2 Contemporary Comfort | P58: 2 OMP T1 8D
A59: One Madison | B59: 28 OMP T3 5M | C59: ACTIVE | D59: VIBER | E59: Studio | F59: Cynthia Mansueto | G59: cynthiamansueto@yahoo.com.ph | H59: (+63) 926 319 4338 | I59: Partnership | J59: 45624 | K59: 45989 | L59: =ifs(C59="INACTIVE","INACTIVE",C59="IN PROGRESS","IN PROGRESS",K59="","",K59="MISSING","?",K59-TODAY()>0,K59-TODAY(),K59-TODAY()<0,"EXPIRED") -> EXPIRED | M59: 28 OMP T3 5M - MANSUETO.pdf | N59: 28 OMP T3 5M | O59: 28 Central Location King Studio | P59: 28 OMP T3 5M
A60: One Madison | B60: 11 OMP T2 5P | C60: ACTIVE | D60: VIBER | E60: Studio | F60: Ernestine Valle | G60: enitsenrevalle@gmail.com | H60: (+63) 917 859 3048 | I60: Partnership | J60: 45627 | K60: 45809 | L60: =ifs(C60="INACTIVE","INACTIVE",C60="IN PROGRESS","IN PROGRESS",K60="","",K60="MISSING","?",K60-TODAY()>0,K60-TODAY(),K60-TODAY()<0,"EXPIRED") -> EXPIRED | M60: 11 OMP T2 5P - VALLE.pdf | N60: 11 OMP T2 5P | O60: 11 Warm and Cozy Studio | P60: 11 OMP T2 5P
A61: One Madison | B61: `1`123wwassdfdxdx dxcxcvxcvc vbvx cvb987yt6432qw1 | D61: VIBER | E61: 1-Bedroom | F61: Hyacinth Faraon | G61: Hyacinth.9@hotmail.com | I61: Fixed | J61: 45524 | K61: 45889 | L61: =ifs(C61="INACTIVE","INACTIVE",C61="IN PROGRESS","IN PROGRESS",K61="","",K61="MISSING","?",K61-TODAY()>0,K61-TODAY(),K61-TODAY()<0,"EXPIRED") -> EXPIRED | M61: 20 OMP T1 9S - FARAON.pdf | N61: 20 OMP T1 9S | O61: 20 Pool View Studio Bliss | P61: 20 OMP T1 9S
A62: One Madison | B62: 38 OMP T1 9N | C62: ACTIVE | D62: VIBER | E62: Studio | F62: Maria Nelia Elvias | G62: kemonel2015@gmail.com | H62: (+63) 951 669 7674 | I62: Partnership | J62: 45738 | K62: 45922 | L62: =ifs(C62="INACTIVE","INACTIVE",C62="IN PROGRESS","IN PROGRESS",K62="","",K62="MISSING","?",K62-TODAY()>0,K62-TODAY(),K62-TODAY()<0,"EXPIRED") -> EXPIRED | M62: 38 OMP T1 9N - ELVIAS.pdf | N62: 38 OMP T1 9N | O62: 38 Cozy Urban Hideaway | P62: 38 OMP T1 9N
A63: One Madison | B63: 27 OMP T3 5N | C63: ACTIVE | D63: VIBER | E63: Studio | F63: Ellen Lacson | G63: lacselle08@gmail.com | I63: Partnership | J63: 45612 | K63: 45977 | L63: =ifs(C63="INACTIVE","INACTIVE",C63="IN PROGRESS","IN PROGRESS",K63="","",K63="MISSING","?",K63-TODAY()>0,K63-TODAY(),K63-TODAY()<0,"EXPIRED") -> EXPIRED | M63: 27 OMP T3 5N - LACSON.pdf | N63: 27 OMP T3 5N | O63: 27 Chic and Spacious Studio | P63: 27 OMP T3 5N
A64: One Madison | B64: 40 OMP T1 7U | C64: ACTIVE | D64: VIBER | E64: Studio | F64: Millicent Tiu | G64: millicent.sy.tiu@gmail.com | L64: =ifs(C64="INACTIVE","INACTIVE",C64="IN PROGRESS","IN PROGRESS",K64="","",K64="MISSING","?",K64-TODAY()>0,K64-TODAY(),K64-TODAY()<0,"EXPIRED") | N64: 40 OMP T1 7U | O64: 40 Minimalist Haven | P64: 40 OMP T1 7U
A65: One Madison | B65: 19 OMP T1 4E | C65: ACTIVE | D65: VIBER | E65: Studio | F65: Robert Javellana | G65: rjjavellana67@yahoo.com | I65: Partnership | J65: 45533 | K65: 45898 | L65: =ifs(C65="INACTIVE","INACTIVE",C65="IN PROGRESS","IN PROGRESS",K65="","",K65="MISSING","?",K65-TODAY()>0,K65-TODAY(),K65-TODAY()<0,"EXPIRED") -> EXPIRED | M65: 19 OMP T1 4E - JAVELLANA.pdf | N65: 19 OMP T1 4E | O65: 19 Cityscape Views | P65: 19 OMP T1 4E
A66: One Madison | B66: 31 OMP T2 4B | C66: ACTIVE | D66: VIBER | E66: Studio | F66: Rodel Alimpoyo | G66: rodel5alimpoyo@yahoo.com.ph | I66: Partnership | J66: 45639 | K66: 46004 | L66: =ifs(C66="INACTIVE","INACTIVE",C66="IN PROGRESS","IN PROGRESS",K66="","",K66="MISSING","?",K66-TODAY()>0,K66-TODAY(),K66-TODAY()<0,"EXPIRED") -> EXPIRED | M66: 31 OMP T2 4B - ALIMPOYO.pdf | N66: 31 OMP T2 4B | O66: 31 Budget-Friendly Studio | P66: 31 OMP T2 4B
A67: One Madison | B67: 12 OMP T3 9K | C67: ACTIVE | D67: VIBER | E67: 1-Bedroom | F67: Chris Tan | G67: tan_albert71@yahoo.com | I67: Partnership | J67: 45446 | K67: 45811 | L67: =ifs(C67="INACTIVE","INACTIVE",C67="IN PROGRESS","IN PROGRESS",K67="","",K67="MISSING","?",K67-TODAY()>0,K67-TODAY(),K67-TODAY()<0,"EXPIRED") -> EXPIRED | M67: 12 OMP T3 9K - TAN.pdf | N67: 12 OMP T3 9K | O67: 12 Modern Sanctuary | P67: 12 OMP T3 9K
A68: One Spatial | B68: OS 4 1316 | C68: ACTIVE | D68: MESSENGER | E68: 2-Bedroom | F68: Ramona Beck | G68: mona_beck2001@yahoo.com | H68: (+63) 935 489 5373 | I68: Partnership | J68: 45635 | K68: 46000 | L68: =ifs(C68="INACTIVE","INACTIVE",C68="IN PROGRESS","IN PROGRESS",K68="","",K68="MISSING","?",K68-TODAY()>0,K68-TODAY(),K68-TODAY()<0,"EXPIRED") -> EXPIRED | N68: OS 4 1316 | O68: OS 4 Family Suite Near Esplanade
A69: One Spatial | B69: OS 5 1318 | C69: ACTIVE | D69: MESSENGER | E69: 2-Bedroom | F69: Ramona Beck | G69: mona_beck2001@yahoo.com | H69: (+63) 935 489 5373 | I69: Partnership | J69: 45635 | K69: 46000 | L69: =ifs(C69="INACTIVE","INACTIVE",C69="IN PROGRESS","IN PROGRESS",K69="","",K69="MISSING","?",K69-TODAY()>0,K69-TODAY(),K69-TODAY()<0,"EXPIRED") -> EXPIRED | N69: OS 5 1318 | O69: OS 5 Barkada Suite Near Esplanade
A70: One Spatial | B70: OS 2 1327 | C70: ACTIVE | D70: NOT YET | E70: 2-Bedroom | F70: Gaudelyn Delfin | G70: gaudelfin23@gmail.com | H70: (+63) 919 992 2476 | I70: Partnership | J70: 45553 | K70: 45918 | L70: =ifs(C70="INACTIVE","INACTIVE",C70="IN PROGRESS","IN PROGRESS",K70="","",K70="MISSING","?",K70-TODAY()>0,K70-TODAY(),K70-TODAY()<0,"EXPIRED") -> EXPIRED | N70: OS 2 1327 | O70: OS 2 Sleek & Stylish 2BR
A71: One Spatial | B71: OS 6 2505 | C71: ACTIVE | D71: VIBER | E71: 2-Bedroom | F71: Charmaine Villareal | G71: chavillareal2017@gmail.com | H71: (+63) 918 985 0231 | I71: Partnership | J71: 45661 | K71: 46026 | L71: =ifs(C71="INACTIVE","INACTIVE",C71="IN PROGRESS","IN PROGRESS",K71="","",K71="MISSING","?",K71-TODAY()>0,K71-TODAY(),K71-TODAY()<0,"EXPIRED") -> EXPIRED | M71: OS 6 2505 - VILLAREAL.pdf | N71: OS 6 2505 | O71: OS 6 Super Spacious 2BR Near Esplanade
A72: People's Hotel | B72: PC A 511 | C72: ACTIVE | D72: FIXED | E72: Studio | F72: Bryan So | G72: Btls@gmail.com | H72: (+63) 918 888 0111 | I72: Fixed | L72: =ifs(C72="INACTIVE","INACTIVE",C72="IN PROGRESS","IN PROGRESS",K72="","",K72="MISSING","?",K72-TODAY()>0,K72-TODAY(),K72-TODAY()<0,"EXPIRED") | N72: PC A 511 | O72: Top Choice Awardee A 2023 | P72: PC A 511
A73: People's Hotel | B73: PC B 512 | C73: ACTIVE | D73: FIXED | E73: Studio | F73: Bryan So | G73: Btls@gmail.com | I73: Fixed | L73: =ifs(C73="INACTIVE","INACTIVE",C73="IN PROGRESS","IN PROGRESS",K73="","",K73="MISSING","?",K73-TODAY()>0,K73-TODAY(),K73-TODAY()<0,"EXPIRED") | N73: PC B 512 | O73: Top Choice Awardee B 2023 | P73: PC B 512
A74: Saint Dominique | B74: 37 SD NW 5F | C74: ACTIVE | D74: MESSENGER | E74: Studio | F74: Ibrahim Khalilullah Maricar / Marny Ringo | G74: ibrahim.maricar@outlook.com | H74: (+971) 555 911519 | I74: Partnership | J74: 45716 | K74: 46081 | L74: =ifs(C74="INACTIVE","INACTIVE",C74="IN PROGRESS","IN PROGRESS",K74="","",K74="MISSING","?",K74-TODAY()>0,K74-TODAY(),K74-TODAY()<0,"EXPIRED") -> EXPIRED | M74: 37 SD NW 5F - MARICAR.pdf | N74: 37 SD NW 5F | O74: 37 Elegant & Cozy | P74: 37 SD NW 5F
A75: Saint Dominique | B75: 30 SD NW 8B | C75: ACTIVE | D75: VIBER | E75: Studio | F75: Anjo Diansay | G75: anjo.diansay47@gmail.com | H75: (+1) (424) 385 1369 | I75: Partnership | J75: 45245 | K75: MISSING | L75: =ifs(C75="INACTIVE","INACTIVE",C75="IN PROGRESS","IN PROGRESS",K75="","",K75="MISSING","?",K75-TODAY()>0,K75-TODAY(),K75-TODAY()<0,"EXPIRED") -> ? | N75: 30 SD NW 8B | O75: 30 Luxe City Studio | P75: 30 SD NW 8B
A76: Saint Dominique | B76: 33 SD SW 7I | C76: ACTIVE | D76: VIBER | E76: Studio | F76: Joe Geronca | G76: jadgeronca@gmail.com | H76: (+63) 917 317 7203 | I76: Partnership | J76: 45673 | K76: 46038 | L76: =ifs(C76="INACTIVE","INACTIVE",C76="IN PROGRESS","IN PROGRESS",K76="","",K76="MISSING","?",K76-TODAY()>0,K76-TODAY(),K76-TODAY()<0,"EXPIRED") -> EXPIRED | N76: 33 SD SW 7I | O76: 33 Elegant City Studio | P76: 33 SD SW 7I
A77: Saint Dominique | B77: 23 SD SW 8C | C77: ACTIVE | D77: VIBER | E77: Studio | F77: Maricel Hoy | G77: maricelhoy@yahoo.com | H77: (+63) 917 164 9919 | I77: 85/15 Partner | J77: 45791 | K77: 46156 | L77: =ifs(C77="INACTIVE","INACTIVE",C77="IN PROGRESS","IN PROGRESS",K77="","",K77="MISSING","?",K77-TODAY()>0,K77-TODAY(),K77-TODAY()<0,"EXPIRED") -> EXPIRED | M77: SD SW 8C - HOY .pdf | N77: 23 SD SW 8C | O77: 23 Comfy Nest for Three | P77: 23 SD SW 8C
A78: Saint Dominique | B78: 7 SD SW 9G | C78: ACTIVE | D78: VIBER | E78: Studio | F78: Noah Montenegro | G78: noahmontenegro@optimum.net | H78: (+1 ) (203) 219-1427 | I78: Partnership | J78: 45737 | K78: 46102 | L78: =ifs(C78="INACTIVE","INACTIVE",C78="IN PROGRESS","IN PROGRESS",K78="","",K78="MISSING","?",K78-TODAY()>0,K78-TODAY(),K78-TODAY()<0,"EXPIRED") -> EXPIRED | N78: 7 SD 9G SW | O78: 7 Metro View Studio | P78: 7 SD 9G SW
A79: Saint Dominique | B79: 29 SD SW 3I | C79: ACTIVE | D79: VIBER | E79: Studio | F79: Ma Precious Fe Matorres | G79: preciousfematorres@gmail.com | H79: (+63) 961 092 6625 | I79: Partnership | J79: 45818 | K79: 46183 | L79: =ifs(C79="INACTIVE","INACTIVE",C79="IN PROGRESS","IN PROGRESS",K79="","",K79="MISSING","?",K79-TODAY()>0,K79-TODAY(),K79-TODAY()<0,"EXPIRED") -> EXPIRED | M79: SD SW 3I - MATORRES.pdf | N79: 29 SD SW 3i | O79: 29 Chic Studio Escape | P79: 29 SD SW 3I
A80: Saint Honore | B80: 43 SH NW 5T | C80: ACTIVE | D80: MESSENGER | E80: Executive Studio | F80: Mary Jean Bearneza | G80: cornerhome99@gmail.com | H80: (+63) 919 384 4464 | I80: 85/15 Partner | J80: 45805 | K80: 46170 | L80: =ifs(C80="INACTIVE","INACTIVE",C80="IN PROGRESS","IN PROGRESS",K80="","",K80="MISSING","?",K80-TODAY()>0,K80-TODAY(),K80-TODAY()<0,"EXPIRED") -> EXPIRED | M80: SH NW 5T - BEARNEZA.pdf | N80: 43 SH NW 5T
A81: Saint Honore | B81: 26 SH SW 7G | C81: ACTIVE | D81: MESSENGER | E81: Studio | F81: Julius Jacomille | G81: rentwithus.abc@gmail.com | I81: 75/25 Partner | J81: 45579 | K81: 45944 | L81: =ifs(C81="INACTIVE","INACTIVE",C81="IN PROGRESS","IN PROGRESS",K81="","",K81="MISSING","?",K81-TODAY()>0,K81-TODAY(),K81-TODAY()<0,"EXPIRED") -> EXPIRED | M81: 26 SH SW 7G - JACOMILLE.pdf | N81: 26 SH SW 7G | O81: 26 Affordable Luxury Studio | P81: 26 SH SW 7G
A82: Saint Honore | B82: 6 SH SW 5J | C82: INACTIVE | D82: N/A | E82: 2-Bedroom | F82: Lilanie Young | G82: lilanieyoung@gmail.com | H82: (+63) 917 122 8861 | I82: Partnership | J82: 45456 | K82: 45821 | L82: =ifs(C82="INACTIVE","INACTIVE",C82="IN PROGRESS","IN PROGRESS",K82="","",K82="MISSING","?",K82-TODAY()>0,K82-TODAY(),K82-TODAY()<0,"EXPIRED") -> INACTIVE | M82: 6 SH SW 5J - YOUNG.pdf | N82: 6 SH SW 5J | O82: 6 Stylish Escape for Groups
A83: Saint Honore | B83: 21 SH NW 6A | C83: ACTIVE | D83: VIBER | E83: 2-Bedroom | F83: Ernesto Tuvida | G83: hjameprestosa@yahoo.com | H83: (+63) 905 473 8567 | I83: Partnership | J83: 45730 | K83: 45914 | L83: =ifs(C83="INACTIVE","INACTIVE",C83="IN PROGRESS","IN PROGRESS",K83="","",K83="MISSING","?",K83-TODAY()>0,K83-TODAY(),K83-TODAY()<0,"EXPIRED") -> EXPIRED | M83: 21 SH NW 6A - TUVIDA.pdf | N83: 21 SH NW 6A
A84: Saint Honore | B84: 1 SH NW 8C | C84: ACTIVE | D84: VIBER | E84: Studio | F84: Jan Cupid Musa | G84: jancupidmusa@gmail.com | H84: (+1) (469) 974 5979 | I84: Partnership | J84: 45758 | K84: 46123 | L84: =ifs(C84="INACTIVE","INACTIVE",C84="IN PROGRESS","IN PROGRESS",K84="","",K84="MISSING","?",K84-TODAY()>0,K84-TODAY(),K84-TODAY()<0,"EXPIRED") -> EXPIRED | M84: 1 SH NW 8C - MUSA.pdf | N84: 1 SH NW 8C | O84: 1 Parisian Charm Hideaway | P84: 1 SH NW 8C
A85: SMDC | B85: SM 12 BB 515 | C85: ACTIVE | D85: MESSENGER | E85: 1-Bedroom | F85: Ariel Sandoy / Thessa Sandoy | G85: asandoy82@gmail.com / geneselat@gmail.com | H85: (+1) 403 918 0294 | I85: 85/15 Partner | L85: =ifs(C85="INACTIVE","INACTIVE",C85="IN PROGRESS","IN PROGRESS",K85="","",K85="MISSING","?",K85-TODAY()>0,K85-TODAY(),K85-TODAY()<0,"EXPIRED") | N85: SM 12 BB 515 | O85: SM 12 Deluxe for Groups
A86: SMDC | B86: SM 2 BA 215 | C86: ACTIVE | D86: MESSENGER | E86: Studio | F86: Sweden Louise Wu | G86: swedenwu07@gmail.com | H86: (+63) 917 799 1118 | I86: Partnership | J86: 45505 | K86: 45870 | L86: =ifs(C86="INACTIVE","INACTIVE",C86="IN PROGRESS","IN PROGRESS",K86="","",K86="MISSING","?",K86-TODAY()>0,K86-TODAY(),K86-TODAY()<0,"EXPIRED") -> EXPIRED | M86: SM 2 BA 215 - WU.pdf | N86: SM 2 BA 215 | O86: SM 2 Peaceful Retreat Near SM City Iloilo
A87: SMDC | B87: SM 7 BA 509 | C87: ACTIVE | D87: MESSENGER | E87: Studio | F87: Evangeline Figueroa Uy | G87: vangie_257@yahoo.com | I87: Partnership | L87: =ifs(C87="INACTIVE","INACTIVE",C87="IN PROGRESS","IN PROGRESS",K87="","",K87="MISSING","?",K87-TODAY()>0,K87-TODAY(),K87-TODAY()<0,"EXPIRED") | N87: SM 7 BA 509 | O87: SM 7 Simple Studio Near SM
A88: SMDC | B88: SM 8 BA 1115 | C88: ACTIVE | D88: FIXED | E88: Studio | F88: April Kaoli Mayordomo | G88: n/a | H88: n/a | I88: Fixed | L88: =ifs(C88="INACTIVE","INACTIVE",C88="IN PROGRESS","IN PROGRESS",K88="","",K88="MISSING","?",K88-TODAY()>0,K88-TODAY(),K88-TODAY()<0,"EXPIRED") | N88: SM 8 BA 1115 | O88: SM 8 Chic & Compact Studio Near SM City
A89: SMDC | B89: SM 5 BA 1425 | C89: INACTIVE | D89: N/A | E89: Studio | F89: Irish Deysolong | G89: irishdeysolong523@gmail.com | H89: (+63) 998 431 8331 | L89: =ifs(C89="INACTIVE","INACTIVE",C89="IN PROGRESS","IN PROGRESS",K89="","",K89="MISSING","?",K89-TODAY()>0,K89-TODAY(),K89-TODAY()<0,"EXPIRED") -> INACTIVE | M89: SM 5 BA 1425 - DEYSOLONG.pdf | N89: SM 5 BA 1425
A90: SMDC | B90: SM 3 BA 401 | C90: INACTIVE | D90: N/A | E90: Studio | F90: Janette Jarabata | G90: janettejarabata84@gmail.com | H90: (+63) 917 129 8536 | I90: Partnership | J90: 45581 | K90: 45763 | L90: =ifs(C90="INACTIVE","INACTIVE",C90="IN PROGRESS","IN PROGRESS",K90="","",K90="MISSING","?",K90-TODAY()>0,K90-TODAY(),K90-TODAY()<0,"EXPIRED") -> INACTIVE | M90: SM 3 BA 401 - JARABATA.pdf | N90: SM 3 BA 401 | O90: SM 3 Metro Studio Near SM City
A91: SMDC | B91: SM 1 BA 1510 | C91: ACTIVE | D91: NOT YET | E91: Studio | F91: Jeanne Bell Ferrer | G91: jeanne.ferrer75@gmail.com | I91: Partnership | J91: 45502 | K91: 45867 | L91: =ifs(C91="INACTIVE","INACTIVE",C91="IN PROGRESS","IN PROGRESS",K91="","",K91="MISSING","?",K91-TODAY()>0,K91-TODAY(),K91-TODAY()<0,"EXPIRED") -> EXPIRED | N91: SM 1 BA 1510 | O91: SM 1 Simple and Comfortable Studio for 2
A92: SMDC | B92: SM 6 BA 1505 | C92: ACTIVE | D92: NOT YET | E92: Studio | F92: Jovie Catalan | G92: joeviecatalan2017@gmail.com, chonavillaruz@gmail.com | H92: (+63) 995 226 8248 | I92: Partnership | J92: 45688 | K92: 46053 | L92: =ifs(C92="INACTIVE","INACTIVE",C92="IN PROGRESS","IN PROGRESS",K92="","",K92="MISSING","?",K92-TODAY()>0,K92-TODAY(),K92-TODAY()<0,"EXPIRED") -> EXPIRED | N92: SM 6 BA 1505 | O92: SM 6 Cozy Minimalist Studio
A93: SMDC | B93: SM 9 BC 208 | C93: ACTIVE | D93: VIBER | E93: Studio | F93: Jenny May Bantolo / Dan Mark Jurada | G93: juradadanmark8888@gmail.com | H93: (+63) 916 874 5391 (+63) 977 107 1531 | I93: 85/15 Partner | J93: 45708 | K93: 46073 | L93: =ifs(C93="INACTIVE","INACTIVE",C93="IN PROGRESS","IN PROGRESS",K93="","",K93="MISSING","?",K93-TODAY()>0,K93-TODAY(),K93-TODAY()<0,"EXPIRED") -> EXPIRED | M93: SM 9 BC 208 - JURADA.pdf | N93: SM 9 BC 208 | O93: SM 9 Minimalist Luxe Studio Near SM City
A94: SMDC | B94: SM 11 BB 624 | C94: ACTIVE | D94: VIBER | E94: Studio | F94: Karen Go | G94: robkar9@yahoo.com.ph | H94: (+63) 920 928 4645 | I94: Partnership | J94: 45751 | K94: 45934 | L94: =ifs(C94="INACTIVE","INACTIVE",C94="IN PROGRESS","IN PROGRESS",K94="","",K94="MISSING","?",K94-TODAY()>0,K94-TODAY(),K94-TODAY()<0,"EXPIRED") -> EXPIRED | M94: SM 11 BB 624 - GO.pdf | N94: SM 11 BB 624 | O94: SM 11 Spacious Urban Nest
A95: SMDC | B95: SM 4 BA 630 | C95: ACTIVE | D95: VIBER | E95: Studio | F95: Mizzy Rosaldes | G95: rosaldesmizzy@gmail.com | H95: (+63) 938 774 1704 | I95: Partnership | J95: 45593 | K95: 45958 | L95: =ifs(C95="INACTIVE","INACTIVE",C95="IN PROGRESS","IN PROGRESS",K95="","",K95="MISSING","?",K95-TODAY()>0,K95-TODAY(),K95-TODAY()<0,"EXPIRED") -> EXPIRED | M95: SM 4 BA 630 - ROSALDES.pdf | N95: SM 4 BA 630 | O95: SM 4 Simple & Spacious
A96: SMDC | B96: SM 10 BA 1420 | C96: ACTIVE | D96: VIBER | E96: Studio | F96: Sugar Ganancial / Dina Jaudian | G96: svghbatch7@gmail.com | H96: (+63) 966 670 1370 , (+63) 920 675 9185 | I96: Partnership | J96: 45754 | K96: 45907 | L96: =ifs(C96="INACTIVE","INACTIVE",C96="IN PROGRESS","IN PROGRESS",K96="","",K96="MISSING","?",K96-TODAY()>0,K96-TODAY(),K96-TODAY()<0,"EXPIRED") -> EXPIRED | M96: SM 10 BA 1420 - GANANCIAL/JAUDIAN.pdf | N96: SM 10 BA 1420 | O96: SM 10 Minimalist Serene Spot
A97: The Palladium | B97: 8 TP NW 21B | C97: ACTIVE | D97: MESSENGER | E97: Executive Studio | F97: Amelita Lapating / Eric Noriega | G97: amylapating@yahoo.com | H97: (+1) 661 321 6264 | I97: 85/15 Partner | J97: 45809 | K97: 46174 | L97: =ifs(C97="INACTIVE","INACTIVE",C97="IN PROGRESS","IN PROGRESS",K97="","",K97="MISSING","?",K97-TODAY()>0,K97-TODAY(),K97-TODAY()<0,"EXPIRED") -> EXPIRED | M97: TP NW 21B - LAPATING/NORIEGA | N97: 8 TP NW 21B | O97: 8 Skyline Sunset Suite | P97: 8 TP NW 21B
A98: The Palladium | B98: 14 TP NW 22C | C98: ACTIVE | D98: MESSENGER | E98: Studio | F98: Risty Durbin | G98: ristyd@yahoo.com | I98: Partnership | J98: 45495 | K98: 45860 | L98: =ifs(C98="INACTIVE","INACTIVE",C98="IN PROGRESS","IN PROGRESS",K98="","",K98="MISSING","?",K98-TODAY()>0,K98-TODAY(),K98-TODAY()<0,"EXPIRED") -> EXPIRED | M98: 14 TP NW 22C - DURBIN.pdf | N98: 14 TP NW 22C | O98: 14 Skyline Serenity | P98: 14 TP NW 22C
A99: The Palladium | B99: 15 TP SW 8D | C99: ACTIVE | D99: VIBER | E99: 1-Bedroom | F99: Joan Reyes | G99: joansalmeoreyes@gmail.com | H99: (+63) 923 255 4900 | I99: 85/15 Partner | J99: 45810 | K99: 45967 | L99: =ifs(C99="INACTIVE","INACTIVE",C99="IN PROGRESS","IN PROGRESS",K99="","",K99="MISSING","?",K99-TODAY()>0,K99-TODAY(),K99-TODAY()<0,"EXPIRED") -> EXPIRED | M99: TP SW 8D - REYES.pdf
A100: The Palladium | B100: 13 TP SW 5J | C100: ACTIVE | D100: VIBER | E100: Studio | F100: Ira Villanueva-Valenzuela | G100: villanueva_ira@yahoo.com | H100: (+63) 917 305 2499 | I100: 75/25 Partner | J100: 45474 | K100: 45839 | L100: =ifs(C100="INACTIVE","INACTIVE",C100="IN PROGRESS","IN PROGRESS",K100="","",K100="MISSING","?",K100-TODAY()>0,K100-TODAY(),K100-TODAY()<0,"EXPIRED") -> EXPIRED | M100: 13 TP SW 5J - VILLANUEVA.pdf | N100: 13 TP SW 5J | O100: 13 Peaceful Studio Nook | P100: 13 TP SW 5J
...

Sheet Expiry Tracker
A1: Building | B1: Property | C1: Unit Owner | D1: Classification | E1: Effective Date | F1: Expiry Date | G1: Expiration Days | H1: Status | I1: Contract | J1: Email | K1: Notes | L1: *Cell Order*
A2: ='Owners Info'!A2 -> Avida Storeys 1 | B2: ='Owners Info'!B2 -> P S1 503 | C2: ='Owners Info'!F2 -> Nino Donato Pison | D2: ='Owners Info'!I2 -> Fixed | E2: ='Owners Info'!J2 -> 45184 | F2: ='Owners Info'!K2 -> MISSING | G2: ='Owners Info'!L2 -> ? | H2: ='Owners Info'!C2 -> ACTIVE | I2: ='Owners Info'!M2 | J2: ='Owners Info'!G2 -> n_pison@yahoo.com | L2: 2
A3: ='Owners Info'!A3 -> Avida Storeys 1 | B3: ='Owners Info'!B3 -> S S1 717 | C3: ='Owners Info'!F3 -> Revrose Selyn Pison | D3: ='Owners Info'!I3 -> Fixed | E3: ='Owners Info'!J3 -> 45180 | F3: ='Owners Info'!K3 -> MISSING | G3: ='Owners Info'!L3 -> ? | H3: ='Owners Info'!C3 -> ACTIVE | I3: ='Owners Info'!M3 | J3: ='Owners Info'!G3 -> n_pison@yahoo.com | L3: 3
A4: ='Owners Info'!A4 -> Avida Storeys 1 | B4: ='Owners Info'!B4 -> S1 408 | C4: ='Owners Info'!F4 -> Edgardo Pison | D4: ='Owners Info'!I4 -> Fixed | E4: ='Owners Info'!J4 -> 45180 | F4: ='Owners Info'!K4 -> MISSING | G4: ='Owners Info'!L4 -> ? | H4: ='Owners Info'!C4 -> ACTIVE | I4: ='Owners Info'!M4 | J4: ='Owners Info'!G4 -> n_pison@yahoo.com | L4: 4
A5: ='Owners Info'!A5 -> Avida Storeys 1 | B5: ='Owners Info'!B5 -> S2 S1 210 | C5: ='Owners Info'!F5 -> Dondon Pison | D5: ='Owners Info'!I5 -> Fixed | E5: ='Owners Info'!J5 -> 45458 | F5: ='Owners Info'!K5 -> 46188 | G5: ='Owners Info'!L5 -> EXPIRED | H5: ='Owners Info'!C5 -> ACTIVE | I5: ='Owners Info'!M5 | J5: ='Owners Info'!G5 -> n_pison@yahoo.com | L5: 5
A6: ='Owners Info'!A6 -> Avida Storeys 1 | B6: ='Owners Info'!B6 -> H S1 506 | C6: ='Owners Info'!F6 -> Bacolod Concept Realty Corp. | D6: ='Owners Info'!I6 -> Fixed | E6: ='Owners Info'!J6 -> 45061 | F6: ='Owners Info'!K6 -> MISSING | G6: ='Owners Info'!L6 -> INACTIVE | H6: ='Owners Info'!C6 -> INACTIVE | I6: ='Owners Info'!M6 | J6: ='Owners Info'!G6 -> n_pison@yahoo.com | L6: 6
A7: ='Owners Info'!A7 -> Avida Storeys 1 | B7: ='Owners Info'!B7 -> Y S1 704 | C7: ='Owners Info'!F7 -> Goldamier Ybera Chua | D7: ='Owners Info'!I7 -> Partnership | E7: ='Owners Info'!J7 -> 45717 | F7: ='Owners Info'!K7 -> 46082 | G7: ='Owners Info'!L7 -> EXPIRED | H7: ='Owners Info'!C7 -> ACTIVE | I7: ='Owners Info'!M7 | J7: ='Owners Info'!G7 -> goldameirchua@gycmarketingopc.com | L7: 7
A8: ='Owners Info'!A8 -> Avida Storeys 2 | B8: ='Owners Info'!B8 -> Y2 S2 203 | C8: ='Owners Info'!F8 -> Ma. Crislyne Mae Espinosa | D8: ='Owners Info'!I8 -> Partnership | E8: ='Owners Info'!J8 -> 45506 | F8: ='Owners Info'!K8 -> 45871 | G8: ='Owners Info'!L8 -> EXPIRED | H8: ='Owners Info'!C8 -> ACTIVE | I8: ='Owners Info'!M8 -> Y2 S2 203 - ESPINOSA.pdf | J8: ='Owners Info'!G8 -> arlandbarvilla@gmail.com | L8: 8
A9: ='Owners Info'!A9 -> Avida Storeys 2 | B9: ='Owners Info'!B9 -> K2 S2 322 | C9: ='Owners Info'!F9 | D9: ='Owners Info'!I9 -> Fixed | E9: ='Owners Info'!J9 -> 45245 | F9: ='Owners Info'!K9 -> MISSING | G9: ='Owners Info'!L9 -> ? | H9: ='Owners Info'!C9 -> ACTIVE | I9: ='Owners Info'!M9 | J9: ='Owners Info'!G9 -> n_pison@yahoo.com | L9: 9
A10: ='Owners Info'!A10 -> Avida Storeys 2 | B10: ='Owners Info'!B10 -> L S2 716 | C10: ='Owners Info'!F10 -> Raymund Trenas | D10: ='Owners Info'!I10 -> Fixed | E10: ='Owners Info'!J10 -> 45180 | F10: ='Owners Info'!K10 -> MISSING | G10: ='Owners Info'!L10 -> ? | H10: ='Owners Info'!C10 -> ACTIVE | I10: ='Owners Info'!M10 | J10: ='Owners Info'!G10 -> raytrenas@gmail.com | L10: 10
A11: ='Owners Info'!A11 -> Avida Storeys 2 | B11: ='Owners Info'!B11 -> T2 S2 703 | C11: ='Owners Info'!F11 -> Leo Paranpan | D11: ='Owners Info'!I11 -> Partnership | E11: ='Owners Info'!J11 -> 45461 | F11: ='Owners Info'!K11 -> 45826 | G11: ='Owners Info'!L11 -> EXPIRED | H11: ='Owners Info'!C11 -> FOR RENEWAL | I11: ='Owners Info'!M11 -> T2 S2 703 - PARANPAN.pdf | J11: ='Owners Info'!G11 -> lparanpan@yahoo.com | L11: 11
A12: ='Owners Info'!A12 -> Avida Tower 1 | B12: ='Owners Info'!B12 -> D T1 917 | C12: ='Owners Info'!F12 -> Robert Stanley Po | D12: ='Owners Info'!I12 -> Partnership | E12: ='Owners Info'!J12 -> 45809 | F12: ='Owners Info'!K12 -> 46174 | G12: ='Owners Info'!L12 -> EXPIRED | H12: ='Owners Info'!C12 -> ACTIVE | I12: ='Owners Info'!M12 | J12: ='Owners Info'!G12 -> cltpo@icloud.com | L12: 12
A13: ='Owners Info'!A13 -> Avida Tower 1 | B13: ='Owners Info'!B13 -> C3 T1 428 | C13: ='Owners Info'!F13 -> Ramona Beck | D13: ='Owners Info'!I13 -> 75/25 Partner | E13: ='Owners Info'!J13 -> 45635 | F13: ='Owners Info'!K13 -> 46000 | G13: ='Owners Info'!L13 -> EXPIRED | H13: ='Owners Info'!C13 -> ACTIVE | I13: ='Owners Info'!M13 | J13: ='Owners Info'!G13 -> mona_beck2001@yahoo.com | L13: 13
... A20: ='Owners Info'!A20 -> Avida Tower 2 | B20: ='Owners Info'!B20 -> R T2 1423 | C20: ='Owners Info'!F20 -> Irene Lachica | D20: ='Owners Info'!I20 -> Fixed | E20: ='Owners Info'!J20 -> 45184 | F20: ='Owners Info'!K20 -> MISSING | G20: ='Owners Info'!L20 -> ? | H20: ='Owners Info'!C20 -> ACTIVE | I20: ='Owners Info'!M20 | J20: ='Owners Info'!G20 -> irene.lachica@yahoo.com | L20: 20
A21: ='Owners Info'!A22 -> Avida Tower 2 | B21: ='Owners Info'!B22 -> B2 T2 108 | C21: ='Owners Info'!F22 -> Edward Espinosa | D21: ='Owners Info'!I22 -> Fixed | E21: ='Owners Info'!J22 -> 45294 | F21: ='Owners Info'!K22 -> MISSING | G21: ='Owners Info'!L22 -> ? | H21: ='Owners Info'!C22 -> ACTIVE | I21: ='Owners Info'!M22 | J21: ='Owners Info'!G22 -> mariespinosa3185@gmail.com | L21: 21
A22: ='Owners Info'!A23 -> Avida Tower 2 | B22: ='Owners Info'!B23 -> F T2 1020 | C22: ='Owners Info'!F23 -> Kathreen Socorro Piamonte | D22: ='Owners Info'!I23 -> Fixed | E22: ='Owners Info'!J23 -> 45022 | F22: ='Owners Info'!K23 -> MISSING | G22: ='Owners Info'!L23 -> ? | H22: ='Owners Info'!C23 -> ACTIVE | I22: ='Owners Info'!M23 | J22: ='Owners Info'!G23 | L22: 22
A23: ='Owners Info'!A24 -> Avida Tower 2 | B23: ='Owners Info'!B24 -> N T2 421 | C23: ='Owners Info'!F24 -> Roberto Gelvezon | D23: ='Owners Info'!I24 -> Fixed | E23: ='Owners Info'!J24 -> 45143 | F23: ='Owners Info'!K24 | G23: ='Owners Info'!L24 | H23: ='Owners Info'!C24 -> ACTIVE | I23: ='Owners Info'!M24 | J23: ='Owners Info'!G24 | L23: 23
A24: ='Owners Info'!A26 -> Avida Tower 2 | B24: ='Owners Info'!B26 -> X T2 1021 | C24: ='Owners Info'!F26 -> Michael Borro | D24: ='Owners Info'!I26 -> Fixed | E24: ='Owners Info'!J26 -> 45107 | F24: ='Owners Info'!K26 -> 46203 | G24: ='Owners Info'!L26 -> EXPIRED | H24: ='Owners Info'!C26 -> ACTIVE | I24: ='Owners Info'!M26 | J24: ='Owners Info'!G26 | L24: 24
A25: ='Owners Info'!A27 -> Avida Tower 2 | B25: ='Owners Info'!B27 -> H2 T2 521 | C25: ='Owners Info'!F27 -> Maria Rita Jardiolin | D25: ='Owners Info'!I27 -> Fixed | E25: ='Owners Info'!J27 -> 45294 | F25: ='Owners Info'!K27 -> MISSING | G25: ='Owners Info'!L27 -> ? | H25: ='Owners Info'!C27 -> ACTIVE | I25: ='Owners Info'!M27 | J25: ='Owners Info'!G27 -> Ritaj241@yahoo.com | L25: 25
A26: ='Owners Info'!A28 -> Avida Tower 2 | B26: ='Owners Info'!B28 -> Q2 T2 1221 | C26: ='Owners Info'!F28 -> Maria Grace Puertollano | D26: ='Owners Info'!I28 -> Partnership | E26: ='Owners Info'!J28 | F26: ='Owners Info'!K28 | G26: ='Owners Info'!L28 -> INACTIVE | H26: ='Owners Info'!C28 -> INACTIVE | I26: ='Owners Info'!M28 | J26: ='Owners Info'!G28 -> graceuybico@gmail.com | L26: 26
A27: ='Owners Info'!A29 -> Avida Tower 2 | B27: ='Owners Info'!B29 -> A T2 322 | C27: ='Owners Info'!F29 -> Aaron James Sales | D27: ='Owners Info'!I29 -> 85/15 Partner | E27: ='Owners Info'!J29 -> 45729 | F27: ='Owners Info'!K29 -> 45821 | G27: ='Owners Info'!L29 -> EXPIRED | H27: ='Owners Info'!C29 -> ACTIVE | I27: ='Owners Info'!M29 | J27: ='Owners Info'!G29 -> Aaronsales.j@gmail.com | L27: 27
A28: ='Owners Info'!A30 -> Avida Tower 2 | B28: ='Owners Info'!B30 -> # T2 209 | C28: ='Owners Info'!F30 -> Fredilyn Samoro/Katrina Samoro | D28: ='Owners Info'!I30 -> 85/15 Partner | E28: ='Owners Info'!J30 -> 45769 | F28: ='Owners Info'!K30 -> 45961 | G28: ='Owners Info'!L30 -> EXPIRED | H28: ='Owners Info'!C30 -> ACTIVE | I28: ='Owners Info'!M30 | J28: ='Owners Info'!G30 | L28: 28
A29: ='Owners Info'!A31 -> Avida Tower 3 | B29: ='Owners Info'!B31 -> D2 T3 626 | C29: ='Owners Info'!F31 -> Donnave Caramat | D29: ='Owners Info'!I31 -> Fixed | E29: ='Owners Info'!J31 -> 45294 | F29: ='Owners Info'!K31 -> MISSING | G29: ='Owners Info'!L31 -> ? | H29: ='Owners Info'!C31 -> ACTIVE | I29: ='Owners Info'!M31 | J29: ='Owners Info'!G31 -> dgcaramat12@gmail.com | L29: 29
A30: ='Owners Info'!A33 -> Avida Tower 3 | B30: ='Owners Info'!B33 -> I T3 725 | C30: ='Owners Info'!F33 -> Mechelle Balasa Rey | D30: ='Owners Info'!I33 -> Fixed | E30: ='Owners Info'!J33 -> 45070 | F30: ='Owners Info'!K33 -> MISSING | G30: ='Owners Info'!L33 -> INACTIVE | H30: ='Owners Info'!C33 -> INACTIVE | I30: ='Owners Info'!M33 | J30: ='Owners Info'!G33 -> jayson12mendoza15@gmail.com | L30: 30
A31: =#REF! -> #REF! | B31: =#REF! -> #REF! | C31: =#REF! -> #REF! | D31: =#REF! -> #REF! | E31: =#REF! -> #REF! | F31: =#REF! -> #REF! | G31: =#REF! -> #REF! | H31: =#REF! -> #REF! | ... J31: =#REF! -> #REF! | L31: 31
A32: ='Owners Info'!A34 -> Avida Tower 3 | B32: ='Owners Info'!B34 -> B3 T3 1011 | C32: ='Owners Info'!F34 -> Gutierrez Dev. Company | D32: ='Owners Info'!I34 -> 75/25 Partner | E32: ='Owners Info'!J34 -> 45611 | F32: ='Owners Info'!K34 -> MISSING | G32: ='Owners Info'!L34 -> ? | H32: ='Owners Info'!C34 -> ACTIVE | I32: ='Owners Info'!M34 | J32: ='Owners Info'!G34 -> gutierrezdevelopment@gmail.com | L32: 32
A33: ='Owners Info'!A35 -> Avida Tower 3 | B33: ='Owners Info'!B35 -> W2 T3 207 | C33: ='Owners Info'!F35 -> Pancho Bringas / Christine Magallanes | D33: ='Owners Info'!I35 -> Partnership | E33: ='Owners Info'!J35 -> 45506 | F33: ='Owners Info'!K35 -> 45871 | G33: ='Owners Info'!L35 -> EXPIRED | H33: ='Owners Info'!C35 -> ACTIVE | I33: ='Owners Info'!M35 | J33: ='Owners Info'!G35 -> Ceee_m@yahoo.com | L33: 33
A34: ='Owners Info'!A36 -> Avida Tower 3 | B34: ='Owners Info'!B36 -> X2 T3 528 | C34: ='Owners Info'!F36 -> Pancho Bringas / Christine Magallanes | D34: ='Owners Info'!I36 -> Partnership | E34: ='Owners Info'!J36 -> 45506 | F34: ='Owners Info'!K36 -> 45871 | G34: ='Owners Info'!L36 -> EXPIRED | H34: ='Owners Info'!C36 -> ACTIVE | I34: ='Owners Info'!M36 | J34: ='Owners Info'!G36 -> Ceee_m@yahoo.com | L34: 34
A35: ='Owners Info'!A37 -> Avida Tower 3 | B35: ='Owners Info'!B37 -> Z2 T3 526 | C35: ='Owners Info'!F37 -> Czarina Ngan | D35: ='Owners Info'!I37 -> 85/15 Partner | E35: ='Owners Info'!J37 -> 45769 | F35: ='Owners Info'!K37 -> 45869 | G35: ='Owners Info'!L37 -> EXPIRED | H35: ='Owners Info'!C37 -> ACTIVE | I35: ='Owners Info'!M37 | J35: ='Owners Info'!G37 -> e43eee3esdwafcfvfcffvgvgrdcrxseexttfddfddz;;p-p-p= | L35: 35
A36: ='Owners Info'!A38 -> Avida Tower 3 | B36: ='Owners Info'!B38 -> M2 T3 424 | C36: ='Owners Info'!F38 -> Leyson San Juan | D36: ='Owners Info'!I38 -> Partnership | E36: ='Owners Info'!J38 -> 45811 | F36: ='Owners Info'!K38 -> 46176 | G36: ='Owners Info'!L38 -> EXPIRED | H36: ='Owners Info'!C38 -> ACTIVE | I36: ='Owners Info'!M38 | J36: ='Owners Info'!G38 -> leyson37@gmail.com | L36: 36
A37: ='Owners Info'!A39 -> Avida Tower 3 | B37: ='Owners Info'!B39 -> N2 T3 426 | C37: ='Owners Info'!F39 -> Leyson San Juan | D37: ='Owners Info'!I39 -> Partnership | E37: ='Owners Info'!J39 -> 45811 | F37: ='Owners Info'!K39 -> 46176 | G37: ='Owners Info'!L39 -> EXPIRED | H37: ='Owners Info'!C39 -> ACTIVE | I37: ='Owners Info'!M39 | J37: ='Owners Info'!G39 -> leyson37@gmail.com | L37: 37
A38: ='Owners Info'!A40 -> Avida Tower 3 | B38: ='Owners Info'!B40 -> O2 T3 826 | C38: ='Owners Info'!F40 -> Leyson San Juan | D38: ='Owners Info'!I40 -> Partnership | E38: ='Owners Info'!J40 -> 45811 | F38: ='Owners Info'!K40 -> 46176 | G38: ='Owners Info'!L40 -> EXPIRED | H38: ='Owners Info'!C40 -> ACTIVE | I38: ='Owners Info'!M40 -> AT T3 826 - SAN JUAN (RENEWAL).pdf | J38: ='Owners Info'!G40 -> leyson37@gmail.com | L38: 38
A39: ='Owners Info'!A41 -> Avida Tower 4 | B39: ='Owners Info'!B41 -> J2 T4 117 | C39: ='Owners Info'!F41 -> Cherry Villa / Jeseryl Villa | D39: ='Owners Info'!I41 -> 85/15 Partner | E39: ='Owners Info'!J41 -> 45809 | F39: ='Owners Info'!K41 -> 46174 | G39: ='Owners Info'!L41 -> EXPIRED | H39: ='Owners Info'!C41 -> ACTIVE | I39: ='Owners Info'!M41 -> AT T4 117 - PINK/VILLA.pdf | J39: ='Owners Info'!G41 -> kixmd@yahoo.com | L39: 39
A40: ='Owners Info'!A42 -> Bernwood Tower | B40: ='Owners Info'!B42 -> BT 1 1222 | C40: ='Owners Info'!F42 -> Ruth Santisteban Serrato | D40: ='Owners Info'!I42 -> Partnership | E40: ='Owners Info'!J42 -> 45748 | F40: ='Owners Info'!K42 -> 45930 | G40: ='Owners Info'!L42 -> EXPIRED | H40: ='Owners Info'!C42 -> ACTIVE | I40: ='Owners Info'!M42 | J40: ='Owners Info'!G42 -> ruthserrato@yahoo.com | L40: 40
A41: ='Owners Info'!A43 -> Lafayette | B41: ='Owners Info'!B43 -> 6 LPS 16S | C41: ='Owners Info'!F43 -> Christine Ladigohon | D41: ='Owners Info'!I43 -> Partnership | E41: ='Owners Info'!J43 -> 45800 | F41: ='Owners Info'!K43 -> 46349 | G41: ='Owners Info'!L43 -> 88 | H41: ='Owners Info'!C43 -> ACTIVE | I41: ='Owners Info'!M43 -> LPS 16S - LADIGOHON.pdf | J41: ='Owners Info'!G43 -> christineladigohon@gmail.com | L41: 41
A42: ='Owners Info'!A44 -> Lafayette | B42: ='Owners Info'!B44 -> 42 LPS 5E | C42: ='Owners Info'!F44 -> Mary Jean Bearneza | D42: ='Owners Info'!I44 -> 85/15 Partner | E42: ='Owners Info'!J44 -> 45805 | F42: ='Owners Info'!K44 -> 46170 | G42: ='Owners Info'!L44 -> EXPIRED | H42: ='Owners Info'!C44 -> ACTIVE | I42: ='Owners Info'!M44 -> LPS 5E - BEARNEZA.pdf | J42: ='Owners Info'!G44 -> cornerhome99@gmail.com | L42: 42
A43: ='Owners Info'!A45 -> Lafayette | B43: ='Owners Info'!B45 -> 25 LPS 8S | C43: ='Owners Info'!F45 -> Julius Jacomille | D43: ='Owners Info'!I45 -> 75/25 Partner | E43: ='Owners Info'!J45 -> 45579 | F43: ='Owners Info'!K45 -> 45944 | G43: ='Owners Info'!L45 -> EXPIRED | H43: ='Owners Info'!C45 -> ACTIVE | I43: ='Owners Info'!M45 -> 25 LPS 8S - JACOMILLE.pdf | J43: ='Owners Info'!G45 -> rentwithus.abc@gmail.com | L43: 43
... A76: ='Owners Info'!A78 -> Saint Dominique | B76: ='Owners Info'!B78 -> 7 SD SW 9G | C76: ='Owners Info'!F78 -> Noah Montenegro | D76: ='Owners Info'!I78 -> Partnership | E76: ='Owners Info'!J78 -> 45737 | F76: ='Owners Info'!K78 -> 46102 | G76: ='Owners Info'!L78 -> EXPIRED | H76: ='Owners Info'!C78 -> ACTIVE | I76: ='Owners Info'!M78 | J76: ='Owners Info'!G78 -> noahmontenegro@optimum.net | L76: 76
A77: ='Owners Info'!A79 -> Saint Dominique | B77: ='Owners Info'!B79 -> 29 SD SW 3I | C77: =#REF! -> #REF! | D77: ='Owners Info'!I79 -> Partnership | E77: ='Owners Info'!J79 -> 45818 | F77: ='Owners Info'!K79 -> 46183 | G77: ='Owners Info'!L79 -> EXPIRED | H77: ='Owners Info'!C79 -> ACTIVE | I77: ='Owners Info'!M79 -> SD SW 3I - MATORRES.pdf | J77: ='Owners Info'!G79 -> preciousfematorres@gmail.com | L77: 77
A78: ='Owners Info'!A80 -> Saint Honore | B78: ='Owners Info'!B80 -> 43 SH NW 5T | C78: ='Owners Info'!F79 -> Ma Precious Fe Matorres | D78: ='Owners Info'!I80 -> 85/15 Partner | E78: ='Owners Info'!J80 -> 45805 | F78: ='Owners Info'!K80 -> 46170 | G78: ='Owners Info'!L80 -> EXPIRED | H78: ='Owners Info'!C80 -> ACTIVE | I78: ='Owners Info'!M80 -> SH NW 5T - BEARNEZA.pdf | J78: ='Owners Info'!G80 -> cornerhome99@gmail.com | L78: 78
A79: ='Owners Info'!A81 -> Saint Honore | B79: ='Owners Info'!B81 -> 26 SH SW 7G | C79: ='Owners Info'!F81 -> Julius Jacomille | D79: ='Owners Info'!I81 -> 75/25 Partner | E79: ='Owners Info'!J81 -> 45579 | F79: ='Owners Info'!K81 -> 45944 | G79: ='Owners Info'!L81 -> EXPIRED | H79: ='Owners Info'!C81 -> ACTIVE | I79: ='Owners Info'!M81 -> 26 SH SW 7G - JACOMILLE.pdf | J79: ='Owners Info'!G81 -> rentwithus.abc@gmail.com | L79: 79
A80: ='Owners Info'!A82 -> Saint Honore | B80: ='Owners Info'!B82 -> 6 SH SW 5J | C80: ='Owners Info'!F82 -> Lilanie Young | D80: ='Owners Info'!I82 -> Partnership | E80: ='Owners Info'!J82 -> 45456 | F80: ='Owners Info'!K82 -> 45821 | G80: ='Owners Info'!L82 -> INACTIVE | H80: ='Owners Info'!C82 -> INACTIVE | I80: ='Owners Info'!M82 -> 6 SH SW 5J - YOUNG.pdf | J80: ='Owners Info'!G82 -> lilanieyoung@gmail.com | L80: 80
A81: ='Owners Info'!A83 -> Saint Honore | B81: ='Owners Info'!B83 -> 21 SH NW 6A | C81: ='Owners Info'!F83 -> Ernesto Tuvida | D81: ='Owners Info'!I83 -> Partnership | E81: ='Owners Info'!J83 -> 45730 | F81: ='Owners Info'!K83 -> 45914 | G81: ='Owners Info'!L83 -> EXPIRED | H81: ='Owners Info'!C83 -> ACTIVE | I81: ='Owners Info'!M83 -> 21 SH NW 6A - TUVIDA.pdf | J81: ='Owners Info'!G83 -> hjameprestosa@yahoo.com | L81: 81
A82: ='Owners Info'!A84 -> Saint Honore | B82: ='Owners Info'!B84 -> 1 SH NW 8C | C82: ='Owners Info'!F84 -> Jan Cupid Musa | D82: ='Owners Info'!I84 -> Partnership | E82: ='Owners Info'!J84 -> 45758 | F82: ='Owners Info'!K84 -> 46123 | G82: ='Owners Info'!L84 -> EXPIRED | H82: ='Owners Info'!C84 -> ACTIVE | I82: ='Owners Info'!M84 -> 1 SH NW 8C - MUSA.pdf | J82: ='Owners Info'!G84 -> jancupidmusa@gmail.com | L82: 82
A83: ='Owners Info'!A85 -> SMDC | B83: ='Owners Info'!B85 -> SM 12 BB 515 | C83: ='Owners Info'!F85 -> Ariel Sandoy / Thessa Sandoy | D83: ='Owners Info'!I85 -> 85/15 Partner | E83: ='Owners Info'!J85 | F83: ='Owners Info'!K85 | G83: ='Owners Info'!L85 | H83: ='Owners Info'!C85 -> ACTIVE | I83: ='Owners Info'!M85 | J83: ='Owners Info'!G85 -> asandoy82@gmail.com / geneselat@gmail.com | L83: 83
A84: ='Owners Info'!A86 -> SMDC | B84: ='Owners Info'!B86 -> SM 2 BA 215 | C84: ='Owners Info'!F86 -> Sweden Louise Wu | D84: ='Owners Info'!I86 -> Partnership | E84: ='Owners Info'!J86 -> 45505 | F84: ='Owners Info'!K86 -> 45870 | G84: ='Owners Info'!L86 -> EXPIRED | H84: ='Owners Info'!C86 -> ACTIVE | I84: ='Owners Info'!M86 -> SM 2 BA 215 - WU.pdf | J84: ='Owners Info'!G86 -> swedenwu07@gmail.com | L84: 84
A85: ='Owners Info'!A87 -> SMDC | B85: ='Owners Info'!B87 -> SM 7 BA 509 | C85: ='Owners Info'!F87 -> Evangeline Figueroa Uy | D85: ='Owners Info'!I87 -> Partnership | E85: ='Owners Info'!J87 | F85: ='Owners Info'!K87 | G85: ='Owners Info'!L87 | H85: ='Owners Info'!C87 -> ACTIVE | I85: ='Owners Info'!M87 | J85: ='Owners Info'!G87 -> vangie_257@yahoo.com | L85: 85
A86: ='Owners Info'!A88 -> SMDC | B86: ='Owners Info'!B88 -> SM 8 BA 1115 | C86: ='Owners Info'!F88 -> April Kaoli Mayordomo | D86: ='Owners Info'!I88 -> Fixed | E86: ='Owners Info'!J88 | F86: ='Owners Info'!K88 | G86: ='Owners Info'!L88 | H86: ='Owners Info'!C88 -> ACTIVE | I86: ='Owners Info'!M88 | J86: ='Owners Info'!G88 -> n/a | L86: 86
A87: ='Owners Info'!A89 -> SMDC | B87: ='Owners Info'!B89 -> SM 5 BA 1425 | C87: ='Owners Info'!F89 -> Irish Deysolong | D87: ='Owners Info'!I89 | E87: ='Owners Info'!J89 | F87: ='Owners Info'!K89 | G87: ='Owners Info'!L89 -> INACTIVE | H87: ='Owners Info'!C89 -> INACTIVE | I87: ='Owners Info'!M89 -> SM 5 BA 1425 - DEYSOLONG.pdf | J87: ='Owners Info'!G89 -> irishdeysolong523@gmail.com | L87: 87
A88: ='Owners Info'!A90 -> SMDC | B88: ='Owners Info'!B90 -> SM 3 BA 401 | C88: ='Owners Info'!F90 -> Janette Jarabata | D88: ='Owners Info'!I90 -> Partnership | E88: ='Owners Info'!J90 -> 45581 | F88: ='Owners Info'!K90 -> 45763 | G88: ='Owners Info'!L90 -> INACTIVE | H88: ='Owners Info'!C90 -> INACTIVE | I88: ='Owners Info'!M90 -> SM 3 BA 401 - JARABATA.pdf | J88: ='Owners Info'!G90 -> janettejarabata84@gmail.com | L88: 88
A89: ='Owners Info'!A91 -> SMDC | B89: ='Owners Info'!B91 -> SM 1 BA 1510 | C89: ='Owners Info'!F91 -> Jeanne Bell Ferrer | D89: ='Owners Info'!I91 -> Partnership | E89: ='Owners Info'!J91 -> 45502 | F89: ='Owners Info'!K91 -> 45867 | G89: ='Owners Info'!L91 -> EXPIRED | H89: ='Owners Info'!C91 -> ACTIVE | I89: ='Owners Info'!M91 | J89: ='Owners Info'!G91 -> jeanne.ferrer75@gmail.com | L89: 89
A90: ='Owners Info'!A92 -> SMDC | B90: ='Owners Info'!B92 -> SM 6 BA 1505 | C90: ='Owners Info'!F92 -> Jovie Catalan | D90: ='Owners Info'!I92 -> Partnership | E90: ='Owners Info'!J92 -> 45688 | F90: ='Owners Info'!K92 -> 46053 | G90: ='Owners Info'!L92 -> EXPIRED | H90: ='Owners Info'!C92 -> ACTIVE | I90: ='Owners Info'!M92 | J90: ='Owners Info'!G92 -> joeviecatalan2017@gmail.com, chonavillaruz@gmail.com | L90: 90
... A122: ='Owners Info'!A124 -> WV Towers | B122: ='Owners Info'!B124 -> WV 1 T1 519 | C122: ='Owners Info'!F124 -> Ruby Arroyo | D122: ='Owners Info'!I124 | E122: ='Owners Info'!J124 -> 45779 | F122: ='Owners Info'!K124 -> 46144 | G122: ='Owners Info'!L124 -> EXPIRED | H122: ='Owners Info'!C124 -> ACTIVE | I122: ='Owners Info'!M124 | J122: ='Owners Info'!G124 -> rubyarroyo70@yahoo.com | L122: 122
A123: =#REF! -> #REF! | B123: =#REF! -> #REF! | C123: =#REF! -> #REF! | D123: =#REF! -> #REF! | E123: =#REF! -> #REF! | F123: =#REF! -> #REF! | G123: =#REF! -> #REF! | H123: =#REF! -> #REF! | ... J123: =#REF! -> #REF! | L123: 123
A124: ='Owners Info'!A125 -> WV Towers | B124: ='Owners Info'!B125 -> WV 10 T2 914 | C124: ='Owners Info'!F125 -> Julius Barvilla | D124: ='Owners Info'!I125 -> 75/25 Partner | E124: ='Owners Info'!J125 -> 45779 | F124: ='Owners Info'!K125 -> 46144 | G124: ='Owners Info'!L125 -> EXPIRED | H124: ='Owners Info'!C125 -> ACTIVE | I124: ='Owners Info'!M125 -> WV 10 T2 914 - BARAVILLA.pdf | J124: ='Owners Info'!G125 -> barvillaj@gmail.com | L124: 124
A125: ='Owners Info'!A126 -> WV Towers | B125: ='Owners Info'!B126 -> WV 19 T1 802 | C125: ='Owners Info'!F126 -> Juzziel Magno | D125: ='Owners Info'!I126 -> 75/25 Partner | E125: ='Owners Info'!J126 -> 45628 | F125: ='Owners Info'!K126 -> 45993 | G125: ='Owners Info'!L126 -> EXPIRED | H125: ='Owners Info'!C126 -> ACTIVE | I125: ='Owners Info'!M126 -> WV 19 T1 802 - MAGNO.pdf | J125: ='Owners Info'!G126 -> juzzy.magno@yahoo.com | L125: 125
A126: ='Owners Info'!A127 -> Avida Tower 1 | B126: ='Owners Info'!B127 -> O T1 1507 | C126: ='Owners Info'!F127 -> Yvonne Chiu | D126: ='Owners Info'!I127 -> Fixed | E126: ='Owners Info'!J127 -> 45152 | F126: ='Owners Info'!K127 | G126: ='Owners Info'!L127 | H126: ='Owners Info'!C127 -> ACTIVE | I126: ='Owners Info'!M127 | J126: ='Owners Info'!G127 | L126: 126
A127: ='Owners Info'!A128 -> Avida Tower 2 | B127: ='Owners Info'!B128 -> K T2 708 | C127: ='Owners Info'!F128 -> Kathreen Socorro Piamonte | D127: ='Owners Info'!I128 -> Fixed | E127: ='Owners Info'!J128 -> 45092 | F127: ='Owners Info'!K128 -> 46188 | G127: ='Owners Info'!L128 -> EXPIRED | H127: ='Owners Info'!C128 -> ACTIVE | I127: ='Owners Info'!M128 | J127: ='Owners Info'!G128 | L127: 127
A128: ='Owners Info'!A129 -> Avida Tower 2 | B128: ='Owners Info'!B129 -> R2 T2 1223 | C128: ='Owners Info'!F129 | D128: ='Owners Info'!I129 -> Fixed | E128: ='Owners Info'!J129 | F128: ='Owners Info'!K129 | G128: ='Owners Info'!L129 | H128: ='Owners Info'!C129 -> ACTIVE | I128: ='Owners Info'!M129 | J128: ='Owners Info'!G129 | L128: 128
A129: ='Owners Info'!A130 -> Avida Tower 2 | B129: ='Owners Info'!B130 -> W T2 1008 | C129: ='Owners Info'!F130 -> Roy Sio | D129: ='Owners Info'!I130 -> Fixed | E129: ='Owners Info'!J130 | F129: ='Owners Info'!K130 | G129: ='Owners Info'!L130 | H129: ='Owners Info'!C130 -> ACTIVE | I129: ='Owners Info'!M130 | J129: ='Owners Info'!G130 | L129: 129
A130: ='Owners Info'!A131 -> Avida Tower 3 | B130: ='Owners Info'!B131 -> J T3 812 | C130: ='Owners Info'!F131 -> Vincent Flaminian | D130: ='Owners Info'!I131 -> Fixed | E130: ='Owners Info'!J131 -> 45092 | F130: ='Owners Info'!K131 -> MISSING | G130: ='Owners Info'!L131 -> ? | H130: ='Owners Info'!C131 -> ACTIVE | I130: ='Owners Info'!M131 | J130: ='Owners Info'!G131 | L130: 130
A131: ='Owners Info'!A132 -> Avida Tower 3 | B131: ='Owners Info'!B132 -> M T3 610 | C131: ='Owners Info'!F132 -> Vanessa Versola | D131: ='Owners Info'!I132 -> Fixed | E131: ='Owners Info'!J132 -> 45100 | F131: ='Owners Info'!K132 -> 46196 | G131: ='Owners Info'!L132 -> EXPIRED | H131: ='Owners Info'!C132 -> ACTIVE | I131: ='Owners Info'!M132 | J131: ='Owners Info'!G132 | L131: 131
A132: ='Owners Info'!A133 -> Avida Tower 3 | B132: ='Owners Info'!B133 -> V T3 909 | C132: ='Owners Info'!F133 -> Meliton Bedia Oso | D132: ='Owners Info'!I133 -> Fixed | E132: ='Owners Info'!J133 | F132: ='Owners Info'!K133 | G132: ='Owners Info'!L133 | H132: ='Owners Info'!C133 -> ACTIVE | I132: ='Owners Info'!M133 | J132: ='Owners Info'!G133 | L132: 132
A133: ='Owners Info'!A134 -> Avida Tower 1 | B133: ='Owners Info'!B134 -> G T1 1009 | C133: ='Owners Info'!F134 -> Rony Armonio | D133: ='Owners Info'!I134 -> Fixed | E133: ='Owners Info'!J134 | F133: ='Owners Info'!K134 | G133: ='Owners Info'!L134 -> INACTIVE | H133: ='Owners Info'!C134 -> INACTIVE | I133: ='Owners Info'!M134 | J133: ='Owners Info'!G134 | L133: 133
A134: ='Owners Info'!A135 -> Avida Tower 1 | B134: ='Owners Info'!B135 -> L2 T1 605 | C134: ='Owners Info'!F135 -> Raquel Sara | D134: ='Owners Info'!I135 -> Fixed | E134: ='Owners Info'!J135 | F134: ='Owners Info'!K135 | G134: ='Owners Info'!L135 -> INACTIVE | H134: ='Owners Info'!C135 -> INACTIVE | I134: ='Owners Info'!M135 | J134: ='Owners Info'!G135 | L134: 134
A135: ='Owners Info'!A136 -> Lafayette | B135: ='Owners Info'!B136 -> 36 LPS 3T | C135: ='Owners Info'!F136 | D135: ='Owners Info'!I136 | E135: ='Owners Info'!J136 | F135: ='Owners Info'!K136 | G135: ='Owners Info'!L136 -> INACTIVE | H135: ='Owners Info'!C136 -> INACTIVE | I135: ='Owners Info'!M136 -> 36 LPS 3T - MERCADO.pdf | J135: ='Owners Info'!G136 | L135: 135
... A139: ='Owners Info'!A140 -> The Palladium | B139: ='Owners Info'!B140 -> 10 TP SW 9E | C139: ='Owners Info'!F140 -> Arlene Tirador | D139: ='Owners Info'!I140 -> Partnership | E139: ='Owners Info'!J140 -> 45413 | F139: ='Owners Info'!K140 -> 45778 | G139: ='Owners Info'!L140 -> EXPIRED | H139: ='Owners Info'!C140 -> ACTIVE | I139: ='Owners Info'!M140 -> 10 TP SW 9E - TIRADOR.pdf | J139: ='Owners Info'!G140 | L139: 139
A140: =#REF! -> #REF! | B140: =#REF! -> #REF! | C140: =#REF! -> #REF! | D140: =#REF! -> #REF! | E140: =#REF! -> #REF! | F140: =#REF! -> #REF! | G140: =#REF! -> #REF! | H140: =#REF! -> #REF! | ... J140: =#REF! -> #REF! | L140: 140
A141: =#REF! -> #REF! | B141: =#REF! -> #REF! | C141: =#REF! -> #REF! | D141: =#REF! -> #REF! | E141: =#REF! -> #REF! | F141: =#REF! -> #REF! | G141: =#REF! -> #REF! | H141: =#REF! -> #REF! | ... J141: =#REF! -> #REF! | L141: 141
A142: ='Owners Info'!A141 | B142: ='Owners Info'!B141 | C142: ='Owners Info'!F141 | D142: ='Owners Info'!I141 | E142: ='Owners Info'!J141 | F142: ='Owners Info'!K141 | G142: ='Owners Info'!L141 | H142: ='Owners Info'!C141 | I142: ='Owners Info'!M141 | J142: ='Owners Info'!G141 | L142: 142
A143: ='Owners Info'!A142 | B143: ='Owners Info'!B142 | C143: ='Owners Info'!F142 | D143: ='Owners Info'!I142 | E143: ='Owners Info'!J142 | F143: ='Owners Info'!K142 | G143: ='Owners Info'!L142 | H143: ='Owners Info'!C142 | I143: ='Owners Info'!M142 | J143: ='Owners Info'!G142 | L143: 143
A144: ='Owners Info'!A143 | B144: ='Owners Info'!B143 | C144: ='Owners Info'!F143 | D144: ='Owners Info'!I143 | E144: ='Owners Info'!J143 | F144: ='Owners Info'!K143 | G144: ='Owners Info'!L143 | H144: ='Owners Info'!C143 | I144: ='Owners Info'!M143 | J144: ='Owners Info'!G143 | L144: 144
A145: ='Owners Info'!A144 | B145: ='Owners Info'!B144 | C145: ='Owners Info'!F144 | D145: ='Owners Info'!I144 | E145: ='Owners Info'!J144 | F145: ='Owners Info'!K144 | G145: ='Owners Info'!L144 | H145: ='Owners Info'!C144 | I145: ='Owners Info'!M144 | J145: ='Owners Info'!G144 | L145: 145
A146: ='Owners Info'!A145 | B146: ='Owners Info'!B145 | C146: ='Owners Info'!F145 | D146: ='Owners Info'!I145 | E146: ='Owners Info'!J145 | F146: ='Owners Info'!K145 | G146: ='Owners Info'!L145 | H146: ='Owners Info'!C145 | I146: ='Owners Info'!M145 | J146: ='Owners Info'!G145 | L146: 146
A147: ='Owners Info'!A146 | B147: ='Owners Info'!B146 | C147: ='Owners Info'!F146 | D147: ='Owners Info'!I146 | E147: ='Owners Info'!J146 | F147: ='Owners Info'!K146 | G147: ='Owners Info'!L146 | H147: ='Owners Info'!C146 | I147: ='Owners Info'!M146 | J147: ='Owners Info'!G146 | L147: 147
A148: ='Owners Info'!A146 | B148: ='Owners Info'!B146 | C148: ='Owners Info'!F146 | D148: ='Owners Info'!I146 | E148: ='Owners Info'!J146 | F148: ='Owners Info'!K146 | G148: ='Owners Info'!L146 | H148: ='Owners Info'!C146 | I148: ='Owners Info'!M146 | J148: ='Owners Info'!G146 | L148: 148
A149: ='Owners Info'!A147 | B149: ='Owners Info'!B147 | C149: ='Owners Info'!F147 | D149: ='Owners Info'!I147 | E149: ='Owners Info'!J147 | F149: ='Owners Info'!K147 | G149: ='Owners Info'!L147 | H149: ='Owners Info'!C147 | I149: ='Owners Info'!M147 | J149: ='Owners Info'!G147 | L149: 149
A150: ='Owners Info'!A148 | B150: ='Owners Info'!B148 | C150: ='Owners Info'!F148 | D150: ='Owners Info'!I148 | E150: ='Owners Info'!J148 | F150: ='Owners Info'!K148 | G150: ='Owners Info'!L148 | H150: ='Owners Info'!C148 | I150: ='Owners Info'!M148 | J150: ='Owners Info'!G148 | L150: 150
A151: ='Owners Info'!A149 | B151: ='Owners Info'!B149 | C151: ='Owners Info'!F149 | D151: ='Owners Info'!I149 | E151: ='Owners Info'!J149 | F151: ='Owners Info'!K149 | G151: ='Owners Info'!L149 | H151: ='Owners Info'!C149 | I151: ='Owners Info'!M149 | J151: ='Owners Info'!G149 | L151: 151
A152: ='Owners Info'!A150 | B152: ='Owners Info'!B150 | C152: ='Owners Info'!F150 | D152: ='Owners Info'!I150 | E152: ='Owners Info'!J150 | F152: ='Owners Info'!K150 | G152: ='Owners Info'!L150 | H152: ='Owners Info'!C150 | I152: ='Owners Info'!M150 | J152: ='Owners Info'!G150 | L152: 152
A153: ='Owners Info'!A151 | B153: ='Owners Info'!B151 | C153: =#REF! -> #REF! | D153: ='Owners Info'!I151 | E153: ='Owners Info'!J151 | F153: ='Owners Info'!K151 | G153: ='Owners Info'!L151 | H153: ='Owners Info'!C151 | I153: ='Owners Info'!M151 | J153: ='Owners Info'!G151 | L153: 153
A154: ='Owners Info'!A152 | B154: ='Owners Info'!B152 | C154: =#REF! -> #REF! | D154: ='Owners Info'!I152 | E154: ='Owners Info'!J152 | F154: ='Owners Info'!K152 | G154: ='Owners Info'!L152 | H154: ='Owners Info'!C152 | I154: ='Owners Info'!M152 | J154: ='Owners Info'!G152 | L154: 154
A155: ='Owners Info'!A141 | B155: ='Owners Info'!B141 | C155: ='Owners Info'!F141 | D155: ='Owners Info'!I141 | E155: ='Owners Info'!J141 | F155: ='Owners Info'!K141 | G155: ='Owners Info'!L141 | H155: ='Owners Info'!C141 | I155: ='Owners Info'!M141 | J155: ='Owners Info'!G141 | L155: 155
A156: ='Owners Info'!A142 | B156: ='Owners Info'!B142 | C156: ='Owners Info'!F142 | D156: ='Owners Info'!I142 | E156: ='Owners Info'!J142 | F156: ='Owners Info'!K142 | G156: ='Owners Info'!L142 | H156: ='Owners Info'!C142 | I156: ='Owners Info'!M142 | J156: ='Owners Info'!G142 | L156: 156
A157: ='Owners Info'!A143 | B157: ='Owners Info'!B143 | C157: ='Owners Info'!F143 | D157: ='Owners Info'!I143 | E157: ='Owners Info'!J143 | F157: ='Owners Info'!K143 | G157: ='Owners Info'!L143 | H157: ='Owners Info'!C143 | I157: ='Owners Info'!M143 | J157: ='Owners Info'!G143 | L157: 157
A158: ='Owners Info'!A144 | B158: ='Owners Info'!B144 | C158: ='Owners Info'!F144 | D158: ='Owners Info'!I144 | E158: ='Owners Info'!J144 | F158: ='Owners Info'!K144 | G158: ='Owners Info'!L144 | H158: ='Owners Info'!C144 | I158: ='Owners Info'!M144 | J158: ='Owners Info'!G144 | L158: 158
A159: ='Owners Info'!A145 | B159: ='Owners Info'!B145 | C159: ='Owners Info'!F145 | D159: ='Owners Info'!I145 | E159: ='Owners Info'!J145 | F159: ='Owners Info'!K145 | G159: ='Owners Info'!L145 | H159: ='Owners Info'!C145 | I159: ='Owners Info'!M145 | J159: ='Owners Info'!G145 | L159: 159
A160: ='Owners Info'!A146 | B160: ='Owners Info'!B146 | C160: ='Owners Info'!F146 | D160: ='Owners Info'!I146 | E160: ='Owners Info'!J146 | F160: ='Owners Info'!K146 | G160: ='Owners Info'!L146 | H160: ='Owners Info'!C146 | I160: ='Owners Info'!M146 | J160: ='Owners Info'!G146 | L160: 160
A161: ='Owners Info'!A147 | B161: ='Owners Info'!B147 | C161: ='Owners Info'!F147 | D161: ='Owners Info'!I147 | E161: ='Owners Info'!J147 | F161: ='Owners Info'!K147 | G161: ='Owners Info'!L147 | H161: ='Owners Info'!C147 | I161: ='Owners Info'!M147 | J161: ='Owners Info'!G147 | L161: 161
A162: ='Owners Info'!A148 | B162: ='Owners Info'!B148 | C162: ='Owners Info'!F148 | D162: ='Owners Info'!I148 | E162: ='Owners Info'!J148 | F162: ='Owners Info'!K148 | G162: ='Owners Info'!L148 | H162: ='Owners Info'!C148 | I162: ='Owners Info'!M148 | J162: ='Owners Info'!G148 | L162: 162
A163: ='Owners Info'!A149 | B163: ='Owners Info'!B149 | C163: ='Owners Info'!F149 | D163: ='Owners Info'!I149 | E163: ='Owners Info'!J149 | F163: ='Owners Info'!K149 | G163: ='Owners Info'!L149 | H163: ='Owners Info'!C149 | I163: ='Owners Info'!M149 | J163: ='Owners Info'!G149 | L163: 163
A164: ='Owners Info'!A150 | B164: ='Owners Info'!B150 | C164: ='Owners Info'!F150 | D164: ='Owners Info'!I150 | E164: ='Owners Info'!J150 | F164: ='Owners Info'!K150 | G164: ='Owners Info'!L150 | H164: ='Owners Info'!C150 | I164: ='Owners Info'!M150 | J164: ='Owners Info'!G150 | L164: 164
A165: ='Owners Info'!A151 | B165: ='Owners Info'!B151 | C165: ='Owners Info'!F151 | D165: ='Owners Info'!I151 | E165: ='Owners Info'!J151 | F165: ='Owners Info'!K151 | G165: ='Owners Info'!L151 | H165: ='Owners Info'!C151 | I165: ='Owners Info'!M151 | J165: ='Owners Info'!G151 | L165: 165
A166: ='Owners Info'!A152 | B166: ='Owners Info'!B152 | C166: ='Owners Info'!F152 | D166: ='Owners Info'!I152 | E166: ='Owners Info'!J152 | F166: ='Owners Info'!K152 | G166: ='Owners Info'!L152 | H166: ='Owners Info'!C152 | I166: ='Owners Info'!M152 | J166: ='Owners Info'!G152 | L166: 166
... A299: ='Owners Info'!A285 | B299: ='Owners Info'!B285 | C299: ='Owners Info'!F285 | D299: ='Owners Info'!I285 | E299: ='Owners Info'!J285 | F299: ='Owners Info'!K285 | G299: ='Owners Info'!L285 | H299: ='Owners Info'!C285 | I299: ='Owners Info'!M285 | J299: ='Owners Info'!G285 | L299: 299

Sheet OI-Old
A1: Building | B1: Status | C1: Property | D1: Unit Type | E1: Unit Owner | F1: Email | G1: Contact Number | H1: Classification | I1: Effective Date | J1: Expiry Date | K1: Near Expiry Tracker | L1: Contract | M1: TYPE OF PARTNERSHIP | N1: AIRBNB | O1: BOOKING .COM | P1: AGODA | Q1: HOSTEEVA | R1: YOUR RENTALS | S1: TRIP.COM | T1: INVENTORY LIST
A2: Saint Honore | B2: ACTIVE | C2: 1 SH NW 8C | D2: Studio | E2: Jan Cupid Musa | F2: jancupidmusa@gmail.com | G2: +1 (469) 974-5979 | H2: Partnership | I2: 45730 | J2: 45914 | L2: 1 SH NW 8C - MUSA.pdf | N2: 1 SH NW 8C | O2: 1 Parisian Charm Hideaway | P2: 1 SH NW 8C
A3: Saint Honore | B3: ACTIVE | C3: 4 SH 5M SW | D3: 1-Bedroom | E3: Charizzma Go | F3: gochusc@gmail.com | H3: Fixed | I3: 45859 | J3: 46224 | N3: 4 SH 5M SW | O3: 4 Majestic View | P3: 4 SH 5M SW
A4: Saint Honore | B4: ACTIVE | C4: 26 SH SW 7G | L4: 26 SH SW 7G - JACOMILLE.pdf | N4: 26 SH SW 7G | O4: 26 Affordable Luxury Studio | P4: 26 SH SW 7G
A5: Saint Honore | B5: INACTIVE | C5: 6 SH SW 5J | D5: 2-Bedroom | E5: Lilanie Young | F5: lilanieyoung@gmail.com | G5: 639171228861 | H5: Partnership | I5: 45456 | J5: 45821 | L5: 6 SH SW 5J - YOUNG.pdf | N5: 6 SH SW 5J | O5: 6 Stylish Escape for Groups
A6: Saint Honore | B6: INACTIVE | C6: 17 SH SW 6O | N6: 17 SH SW 6O
A7: Saint Honore | B7: INACTIVE | C7: 15 LPS 10-O | D7: 1-Bedroom | E7: Michael Limsiaco | F7: limsiacomichael@yahoo.com | G7: 639189012626 | H7: Partnership | I7: 45503 | J7: 45868 | L7: 15 LPS 10-O - LIMSIACO.pdf
A8: Saint Honore | B8: INACTIVE | C8: 21 SH NW 6A | D8: 2-Bedroom | E8: Ernesto Tuvida | F8: hjameprestosa@yahoo.com | G8: 639054738567 | H8: Partnership | I8: 45579 | J8: 45944 | L8: 21 SH NW 6A - TUVIDA.pdf | N8: 21 SH NW 6A
A9: Saint Honore | B9: ACTIVE | C9: 24 LPS 9PQ | D9: 1-Bedroom | E9: Risty Durbin | F9: ristyd@yahoo.com | H9: Partnership | I9: 45566 | J9: 45931 | L9: 24 LPS 9PQ - DURBIN.pdf
A10: Saint Dominique | B10: ACTIVE | C10: 7 SD 9G SW | D10: Studio | E10: Noah Montenegro | F10: noahmontenegro@optimum.net | G10: +1 (203) 219-1427 | H10: Partnership | I10: 45737 | J10: 46102 | N10: 7 SD 9G SW | O10: 7 Metro View Studio | P10: 7 SD 9G SW
A11: Saint Dominique | B11: ACTIVE | C11: 23 SD SW 8C | N11: 23 SD SW 8C | O11: 23 Comfy Nest for Three | P11: 23 SD SW 8C
A12: Saint Dominique | B12: ACTIVE | C12: 33 SD SW 7I | D12: Studio | E12: Hyacinth Faraon | F12: Hyacinth.9@hotmail.com | H12: Partnership | I12: 45673 | J12: 46038 | N12: 33 SD SW 7i | O12: 33 Elegant City Studio | P12: 33 SD SW 7I
A13: Saint Dominique | B13: ACTIVE | C13: 37 SD NW 5F | D13: Studio | E13: Cesar Mercado | F13: meres044@yahoo.com | G13: 639156392337 | H13: Partnership | I13: 45714 | J13: 45895 | L13: 37 SD NW 5F - MARICAR.pdf | N13: 37 SD NW 5F | O13: 37 Elegant & Cozy | P13: 37 SD NW 5F
A14: Saint Dominique | B14: ACTIVE | C14: 30 SD NW 8B | D14: Studio | E14: Ramel Uy | F14: Uy_ramel@yahoo.com | H14: Partnership | I14: 45245 | J14: MISSING EXPIRY DATE | N14: 30 SD NW 8B | O14: 30 Luxe City Studio | P14: 30 SD NW 8B
A15: Saint Dominique | B15: ACTIVE | C15: 29 SD SW 3I | D15: Studio | E15: Ma Precious Fe Matorres | F15: preciousfematorres@gmail.com | G15: 639610926625 | H15: Partnership | I15: 45818 | J15: 46183 | L15: 29 SD SW 3i - MATORRES.pdf | N15: 29 SD SW 3i | O15: 29 Chic Studio Escape | P15: 29 SD SW 3I
A16: One Madison Place | B16: ACTIVE | C16: 2 OMP T1 8D | D16: Studio | E16: Risty Durbin | F16: ristyd@yahoo.com | H16: Partnership | I16: 45525 | J16: 45890 | N16: 2 OMP T1 8D | O16: 2 Contemporary Comfort | P16: 2 OMP T1 8D
A17: One Madison Place | B17: ACTIVE | C17: 3 OMP T3 10-O | D17: Studio | E17: Cynthia Mansueto | F17: cynthiamansueto@yahoo.com.ph | G17: 639263194338 | H17: Partnership | I17: 45624 | J17: 45989 | N17: 3 OMP T3 10-O | O17: 3 Iloilo's Dream Studio | P17: 3 OMP T3 10-O
A18: One Madison Place | B18: ACTIVE | C18: 12 OMP T3 9K | D18: 1-Bedroom | E18: Arlene Tirador | F18: febgirl2691@yahoo.com.ph | G18: 639177995554 | H18: Partnership | I18: 45422 | J18: 45787 | L18: 12 OMP T3 9K - TAN.pdf | N18: 12 OMP T3 9K | O18: 12 Modern Sanctuary | P18: 12 OMP T3 9K
A19: One Madison Place | B19: ACTIVE | C19: 19 OMP T1 4E | D19: Studio | E19: Emmanuel Capacio | F19: emmanuelcapacio@gmail.com | H19: Partnership | I19: 45758 | J19: 46123 | L19: 19 OMP T1 4E - JAVELLANA.pdf | N19: 19 OMP T1 4E | O19: 19 Cityscape Views | P19: 19 OMP T1 4E
A20: One Madison Place | B20: ACTIVE | C20: 20 OMP T1 9S | D20: 1-Bedroom | E20: Charizzma Go | F20: gochusc@gmail.com | H20: Fixed | I20: 45750 | J20: 46115 | L20: 20 OMP T1 9S - FARAON.pdf | N20: 20 OMP T1 9S | O20: 20 Pool View Studio Bliss | P20: 20 OMP T1 9S
A21: One Madison Place | B21: ACTIVE | C21: 27 OMP T3 5N | D21: Studio | E21: Julius Jacomille | F21: rentwithus.abc@gmail.com | H21: Partnership | I21: 45579 | J21: 45944 | N21: 27 OMP T3 5N | O21: 27 Chic and Spacious Studio | P21: 27 OMP T3 5N
A22: One Madison Place | B22: ACTIVE | C22: 28 OMP T3 5M | D22: Studio | E22: Julius Jacomille | F22: rentwithus.abc@gmail.com | H22: Partnership | L22: 28 OMP T3 5M - MANSUETO.pdf | N22: 28 OMP T3 5M | O22: 28 Central Location King Studio | P22: 28 OMP T3 5M
A23: One Madison Place | B23: ACTIVE | C23: 31 OMP T2 4B | D23: Studio | E23: Anjo Diansay | F23: anjodiansay@gmail.com | G23: +1 (424) 385-1369 | H23: Partnership | I23: 45635 | J23: 46000 | L23: 31 OMP T2 4B - ALIMPOYO.pdf | N23: 31 OMP T2 4B | O23: 31 Budget-Friendly Studio | P23: 31 OMP T2 4B
A24: One Madison Place | B24: ACTIVE | C24: 38 OMP T1 9N | D24: Studio | E24: Ibrahim Khalilullah Maricar | F24: ibrahim.maricar@outlook.com | H24: Partnership | I24: 45716 | J24: 46081 | N24: 38 OMP T1 9N | O24: 38 Cozy Urban Hideaway | P24: 38 OMP T1 9N
A25: One Madison Place | B25: ACTIVE | C25: 32 OMP T3 10E | D25: Studio | E25: Rodel Alimpoyo | F25: rodel5alimpoyo@yahoo.com.ph | H25: Partnership | I25: 45639 | J25: 46004 | L25: 32 OMP T3 10E - FARAON.pdf | N25: 32 OMP T3 10E | O25: 32 Best Value Family Suite | P25: 32 OMP T3 10E
A26: One Madison Place | B26: ACTIVE | C26: 40 OMP T1 7U | D26: Studio | E26: Millicent Tiu | F26: millicent.sy.tiu@gmail.com | N26: 40 OMP T1 7U | O26: 40 Minimalist Haven | P26: 40 OMP T1 7U
B27: ACTIVE | C27: 11 OMP T2 5P | D27: Studio | E27: Ernestine Valle | F27: enitsenrevalle@gmail.com | G27: 639178593048 | H27: Partnership | I27: 45444 | J27: 45809 | L27: 11 OMP T2 5P - VALLE.pdf | N27: 11 OMP T2 5P | O27: 11 Warm and Cozy Studio | P27: 11 OMP T2 5P
A28: One Madison Place | B28: IN PROGRESS | C28: 41 OMP T3 10K | D28: Studio | E28: Ibrahim Kabeer | F28: ibrahimmaricar@outlook.com | H28: Partnership | I28: 45778 | J28: 46143 | L28: OMP T3 10K
A29: Lafayette | B29: ACTIVE | C29: 5 LPS 16T | D29: Studio | E29: Esther Palmares | F29: Esjoyp@aol.com | G29: 639178989043 | H29: Partnership | I29: 45670 | J29: 46035 | L29: LPS 16T - PALMARES.pdf | N29: 5 LPS 16T | O29: 5 Modern Chic Studio | P29: 5 LPS 16T
A30: Lafayette | B30: ACTIVE | C30: 6 LPS 16S | D30: Studio | E30: Christine Ladigohon | F30: christineladigohon@gmail.com | G30: 9291818824 | H30: Partnership | I30: 45740 | J30: 46166 | N30: 6 LPS 16S | O30: 6 Simple Pearl Retreat | P30: 6 LPS 16S
A31: Lafayette | B31: ACTIVE | C31: 15 LPS 10-O | D31: Studio | E31: Ira Villanueva | F31: villanueva_ira@yahoo.com | G31: 639173052499 | H31: Partnership | I31: 45474 | J31: 45839 | N31: 15 LPS 10-O | O31: 15 Elegant Urban Suite | P31: 15 LPS 10-O
A32: Lafayette | B32: ACTIVE | C32: 16 LPS 15X | D32: Studio | E32: Risty Durbin | F32: ristyd@yahoo.com | H32: Partnership | I32: 45495 | J32: 45860 | L32: 16 LPS 15X - SOLINAP.pdf | N32: 16 LPS 15X | O32: 16 Cozy and Spacious Studio | P32: 16 LPS 15X
A33: Lafayette | B33: ACTIVE | C33: 18 LPS 9R | D33: Studio | E33: Euniel Solinap | F33: euniel.md@gmail.com | G33: 639173208884 | H33: Partnership | I33: 45509 | J33: 45874 | L33: 18 LPS 9R - DURBIN.pdf | N33: 18 LPS 9R | O33: 18 Warm Studio Oasis | P33: 18 LPS 9R
A34: Lafayette | B34: ACTIVE | C34: 22 LPS 8J | D34: Studio | E34: Hyacinth Faraon | F34: Hyacinth.9@hotmail.com | H34: Partnership | I34: 45524 | J34: 45889 | L34: 22 LPS 8J -ZAPANTA.pdf | N34: 22 LPS 8J | O34: 22 Luxurious 1-Bedroom Apartment | P34: 22 LPS 8J
A35: Lafayette | B35: ACTIVE | C35: 24 LPS 9PQ | D35: 1-Bedroom | E35: Adonis Zapanta | F35: dimple_email2@yahoo.com | H35: Partnership | I35: 45531 | J35: 45896 | N35: 24 LPS 9PQ | O35: 24 Modern 1-Bedroom Minimalist Sanctuary | P35: 24 LPS 9PQ
A36: Lafayette | B36: ACTIVE | C36: 25 LPS 8S | D36: Studio | E36: Maricel Hoy | F36: maricelhoy@yahoo.com | H36: Partnership | I36: 45791 | J36: 46156 | L36: 25 LPS 8S - JACOMILLE.pdf | N36: 25 LPS 8S | O36: 25 Central Luxury Studio | P36: 25 LPS 8S
A37: Lafayette | B37: ACTIVE | C37: 34 LPS 5Z | D37: Studio | E37: Antonio Geronca | F37: jadgeronca@gmail.com, ems1215@ymail.com | G37: 639173177203 | H37: Partnership | I37: 45688 | J37: 46053 | L37: 34 LPS 5Z - BELICENA.pdf | N37: 34 LPS 5Z | O37: 34 Retro Chic Studio | P37: 34 LPS 5Z
A38: Lafayette | B38: ACTIVE | C38: 35 LPS 5Y | D38: Studio | E38: Maria Emily Belicena | F38: emilybelicena@gmail.com | G38: 639185702183 | H38: Partnership | I38: 45707 | J38: 46010 | L38: 35 LPS 5Y - BELICENA.pdf | N38: 35 LPS 5Y | O38: 35 Adorable Studio | P38: 35 LPS 5Y
A39: Lafayette | B39: ACTIVE | C39: 36 LPS 3T | D39: Studio | E39: Maria Emily Belicena/Beatriz Karina Belicena | F39: emilybelicena@gmail.com | G39: 639185702183 | H39: Partnership | I39: 45707 | J39: 46010 | L39: 36 LPS 3T - MERCADO.pdf | N39: 36 LPS 3T | O39: 36 Executive Garden Suite | P39: 36 LPS 3T
A40: The Palladium | B40: ACTIVE | C40: 8 TP NW 21B | D40: Executive Studio | E40: Amy Lapating | N40: 8 TP NW 21B | O40: 8 Skyline Sunset Suite | P40: 8 TP NW 21B
A41: The Palladium | B41: ACTIVE | C41: 9 TP NW 10E | D41: 1-Bedroom | H41: Partnership | N41: 9 TP NW 10E | O41: 9 Roomy Urban Escape | P41: 9 TP NW 10E
A42: The Palladium | B42: ACTIVE | C42: 10 TP SW 9E | D42: Studio | E42: Robert Javellana | F42: rjjavellana67@yahoo.com | H42: Partnership | I42: 45533 | J42: 45898 | L42: 10 TP SW 9E - TIRADOR.pdf | N42: 10 TP SW 9E | O42: 10 Luxurious King Suite | P42: 10 TP SW 9E
A43: The Palladium | B43: FOR RENEWAL | C43: 13 TP SW 5J | F43: villanueva_ira@yahoo.com | L43: 13 TP SW 5J - VILLANUEVA.pdf | N43: 13 TP SW 5J | O43: 13 Peaceful Studio Nook | P43: 13 TP SW 5J
A44: The Palladium | B44: FOR RENEWAL | C44: 14 TP NW 22C | D44: Studio | E44: Albert Tan | F44: tan_albert71@yahoo.com | H44: Partnership | I44: 45446 | J44: 45811 | L44: 14 TP NW 22C - DURBIN.pdf | N44: 14 TP NW 22C | O44: 14 Skyline Serenity | P44: 14 TP NW 22C
A45: Avida Tower 1 | B45: FOR RENEWAL | C45: A3 T1 1524 | D45: Studio | E45: Elvie Dofitas | F45: Elvie.dofitas08@gmail.com | G45: 9176800008 | H45: Partnership | I45: 45600 | J45: 45781 | L45: A3 T1 1524 - DOFITAS.pdf | M45: 75/25 | N45: A3 T1 1524 | O45: A3 Central Studio Getaway | P45: A3 T1 1524
A46: Avida Tower 1 | B46: IN PROGRESS | C46: B AT T1 501 | D46: 1-Bedroom | J46: MISSING EXPIRY DATE
A47: Avida Tower 1 | B47: IN PROGRESS | C47: C
A48: Avida Tower 1 | B48: IN PROGRESS | C48: C2
A49: Avida Tower 1 | B49: ACTIVE | C49: C3 T1 428 | D49: 2-Bedroom | E49: Ramona Beck | F49: mona_beck2001@yahoo.com | G49: 639354895373 | H49: Partnership | I49: 45635 | J49: 46000 | N49: C3 T1 428 | O49: C3 Elegant 2BR Condo with Pool View | P49: C3 T1 428
A50: Avida Tower 1 | B50: ACTIVE | C50: D T1 917 | D50: Studio | E50: Robert Stanley Po | F50: cltpo@icloud.com | H50: Partnership | I50: 45809 | J50: 46174 | N50: D T1 917 | O50: D Peaceful and Comfortable Room | P50: D T1 917
A51: Avida Tower 1 | B51: IN PROGRESS | C51: E | D51: N9
A52: Avida Tower 1 | B52: IN PROGRESS | C52: F2
A53: Avida Tower 1 | B53: INACTIVE | C53: G T1 1009 | D53: Studio | E53: Rony Armonio | H53: Fixed | N53: G T1 1009
A54: Avida Tower 1 | B54: IN PROGRESS | C54: G2
A55: Avida Tower 1 | B55: IN PROGRESS | C55: L2 T1 605 | D55: Studio | E55: Raquel Sara | H55: Fixed | N55: L2 T1 605 | O55: L2 Budget Friendly Studio | P55: L2 T1 605
A56: Avida Tower 1 | B56: ACTIVE | C56: O T1 1507 | D56: Studio | E56: Yvonne Chiu | H56: Fixed | I56: 45152 | N56: O T1 1507 | O56: O Simple and Comfortable | P56: O T1 1507
A57: Avida Tower 1 | B57: ACTIVE | C57: U2 T1 221 | D57: 1-Bedroom | E57: Ira Villanueva | F57: villanueva_ira@yahoo.com | G57: 639173052499 | H57: Partnership | I57: 45474 | J57: 45839 | L57: U2 T1 221 - VILLANUEVA.pdf | N57: U2 T1 221 | O57: U2 Spacious 1BR Retreat | P57: U2 T1 221
A58: Avida Tower 1 | B58: IN PROGRESS | C58: V2 T1 306 | D58: Studio | E58: Dondon Pison | F58: n_pison@yahoo.com | H58: Partnership | N58: V2 T1 306 | O58: V2 Relaxing Studio Escape | P58: V2 T1 306
A59: Avida Tower 2 | B59: ACTIVE | C59: A T2 322 | D59: Studio | E59: Aaron James Sales | F59: Aaronsales.j@gmail.com | H59: Partnership | I59: 45729 | J59: 45821 | M59: 85/15 | N59: A T2 322 | O59: A Charming Urban Retreat | P59: A T2 322
A60: Avida Tower 2 | B60: ACTIVE | C60: B2 T2 108 | D60: Studio | E60: Edward Espinosa | F60: mariespinosa3185@gmail.com | H60: Fixed | I60: 45294 | J60: MISSING EXPIRY DATE | N60: B2 T2 108 | O60: B2 Your Go-To Crib
A61: Avida Tower 2 | B61: ACTIVE | C61: E2 T2 309 | D61: Studio | E61: Mary Joyce Torrefranca | F61: cant0910@yahoo.com | G61: 639173195794 | H61: Fixed | I61: 45698 | J61: MISSING EXPIRY DATE | N61: E2 T2 309 | O61: E2 Oasis in the City
A62: Avida Tower 2 | B62: ACTIVE | C62: F T2 1020 | D62: Studio | E62: Kathreen Socorro Piamonte | F62: n_pison@yahoo.com | H62: Fixed | I62: 45022 | J62: MISSING EXPIRY DATE | N62: F T2 1020 | O62: F Best Vlaue in Iloilo | P62: F T2 1020
A63: Avida Tower 2 | B63: ACTIVE | C63: H2 T2 521 | D63: Studio | E63: Maria Rita Jardiolin | F63: Ritaj241@yahoo.com | H63: Fixed | I63: 45294 | J63: MISSING EXPIRY DATE | N63: H2 T2 521 | O63: H2 Modern City Condo | P63: H2 T2 521
A64: Avida Tower 2 | B64: ACTIVE | C64: I2 T2 522 | D64: Studio | E64: Lourdes Carney | F64: Lourdes.carney@gmail.com | H64: Fixed | I64: 45294 | J64: MISSING EXPIRY DATE | N64: I2 T2 522 | O64: I2 Sleek City Haven | P64: I2 T2 522
A65: Avida Tower 2 | B65: IN PROGRESS | C65: J2
A66: Avida Tower 2 | B66: ACTIVE | C66: K T2 708 | D66: Studio | E66: Kathreen Socorro Piamonte | H66: Fixed | I66: 45092 | J66: 46188 | N66: K T2 708 | O66: K Irresistable value for | P66: K T2 708
A67: Avida Tower 2 | B67: IN PROGRESS | C67: N T2 421 | D67: Studio | E67: Roberto Gelvezon | F67: n_pison@yahoo.com | H67: Fixed | I67: 45143 | N67: N T2 421 | O67: N Affordable Urban Luxury | P67: N T2 421
A68: Avida Tower 2 | B68: ACTIVE | C68: Q T2 420 | D68: Studio | E68: Gerard Teofilo Gelvezon | F68: n_pison@yahoo.com | H68: Fixed | I68: 45184 | J68: MISSING EXPIRY DATE | N68: Q T2 420 | O68: Q Incomparable Comfort for 3 | P68: Q T2 420
A69: Avida Tower 2 | B69: ACTIVE | C69: Q2 T2 1221 | D69: Studio | E69: Maria Grace Puertollano | F69: graceuybico@gmail.com | H69: Partnership | N69: Q2 T2 1221 | O69: Q2 City View Twin Room | P69: Q2 T2 1221
A70: Avida Tower 2 | B70: ACTIVE | C70: R T2 1423 | D70: Studio | E70: Irene Lachica | F70: irene.lachica@yahoo.com | G70: 639237415922 | H70: Fixed | I70: 45184 | J70: MISSING EXPIRY DATE | N70: R T2 1423 | O70: R Metropolitan Mirage | P70: R T2 1423
A71: Avida Tower 2 | B71: ACTIVE | C71: R2 T2 1223 | D71: Studio | H71: Fixed | N71: R2 T2 1223 | O71: R2 Minimalist Snug Haven | P71: R2 T2 1223
A72: Avida Tower 2 | B72: ACTIVE | C72: T T2 815 | D72: Studio | E72: William Del Rosario | F72: bdelrosario1014@gmail.com | H72: Fixed | N72: T T2 815 | O72: T Panoramic Metro View | P72: T T2 815
A73: Avida Tower 2 | B73: IN PROGRESS | C73: U
A74: Avida Tower 2 | B74: ACTIVE | C74: W T2 1008 | E74: Roy Sio | H74: Fixed | N74: W T2 1008 | O74: W Prime Location Condo for 3 | P74: W T2 1008
A75: Avida Tower 2 | B75: ACTIVE | C75: X T2 1021 | D75: Studio | E75: Michael Borro | F75: n_pison@yahoo.com | H75: Fixed | I75: 45107 | J75: 46203 | N75: X T2 1021 | O75: X Metro Bliss
A76: Avida Tower 3 | B76: INACTIVE | C76: A2 T3 526 | D76: Studio | E76: Czarina Y. Ngan | F76: cyn8684@gmail.com | H76: Partnership | L76: at the file | N76: A2 T3 526
A77: Avida Tower 3 | B77: ACTIVE | C77: B3 T3 1011 | D77: Studio | E77: Gutierrez Dev. Company | F77: gutierrezdevelopment@gmail.com | H77: Partnership | I77: 45611 | J77: MISSING EXPIRY DATE | M77: 75/25 | N77: B3 T3 1011 | O77: B3 Chic Sunset Studio Escape | P77: B3 T3 1011
A78: Avida Tower 3 | B78: ACTIVE | C78: D2 T3 626 | D78: Studio | E78: Donnave Caramat | F78: dgcaramat12@gmail.com | H78: Fixed | I78: 45294 | J78: MISSING EXPIRY DATE | N78: D2 T3 626 | O78: D2 Central Location Condo
A79: Avida Tower 3 | B79: INACTIVE | C79: I T3 725 | D79: Studio | E79: Mechelle Balasa Rey | F79: jayson12mendoza15@gmail.com | H79: Fixed | I79: 45070 | J79: MISSING EXPIRY DATE | N79: I T3 725 | O79: I Best Value Studio
A80: Avida Tower 3 | B80: ACTIVE | C80: J T3 812 | D80: Studio | E80: Vincent Flaminian | H80: Fixed | I80: 45092 | J80: MISSING EXPIRY DATE | N80: J T3 812 | O80: J Travellers' Choice 2023 | P80: J T3 812
A81: Avida Tower 3 | B81: ACTIVE | C81: M T3 610 | D81: 1-Bedroom | E81: Vanessa Versola | H81: Fixed | I81: 45100 | J81: 46196 | N81: M T3 610 | O81: M Your Iloilo City Sanctuary | P81: M T3 610
A82: Avida Tower 3 | B82: ACTIVE | C82: M2 T3 424 | D82: Studio | E82: Leyson San Juan | F82: leyson37@gmail.com | G82: 639177137994 | H82: Partnership | I82: 45809 | J82: 46174 | N82: M2 T3 424 | O82: M2 Minimalist and Cozy Studio | P82: M2 T3 424
A83: Avida Tower 3 | B83: ACTIVE | C83: N2 T3 426 | D83: Studio | E83: Leyson San Juan | F83: leyson37@gmail.com | G83: 639177137994 | H83: Partnership | I83: 45414 | J83: 45779 | N83: N2 T3 426 | O83: N2 Sleek Urban Escape | P83: N2 T3 426
A84: Avida Tower 3 | B84: ACTIVE | C84: O2 T3 826 | D84: Studio | E84: Leyson San Juan | F84: leyson37@gmail.com | G84: 639177137994 | H84: Partnership | I84: 45414 | J84: 45779 | N84: O2 T3 826 | O84: O2 Urban Zen Retreat | P84: O2 T3 826
A85: Avida Tower 3 | B85: ACTIVE | C85: V T3 909 | D85: 1-Bedroom | E85: Meliton Bedia Oso | H85: Fixed | N85: V T3 909 | O85: V Picturesque Sunset Retreat w/ Washing Machine
A86: Avida Tower 3 | B86: ACTIVE | C86: W2 T3 207 | D86: Studio | E86: Christine Magallanes | F86: Ceee_m@yahoo.com | G86: 639173031696 | H86: Partnership | I86: 45506 | J86: 45871 | N86: W2 T3 207 | O86: W2 Cozy Urban Nest | P86: W2 T3 207
A87: Avida Tower 3 | B87: ACTIVE | C87: X2 T3 528 | D87: Studio | E87: Christine Magallanes | F87: Ceee_m@yahoo.com | G87: 639173031696 | H87: Partnership | I87: 45506 | J87: 45871 | N87: X2 T3 528 | O87: X2 Urban Zen Studio | P87: X2 T3 528
A88: Avida Tower 3 | B88: IN PROGRESS | C88: Z
A89: Avida Tower 3 | B89: ACTIVE | C89: Z2 T3 526 | D89: Studio | E89: Czarina Ngan | F89: cyn8684@gmail.com | G89: 639177018684 | H89: Partnership | I89: 45769 | J89: 45869 | N89: Z2 T3 526 | O89: Z2 Modern Zen Hideaway | P89: Z2 T3 526
A90: Avida Storeys 1 | B90: INACTIVE | C90: H S1 506 | D90: 1-Bedroom | E90: Bacolod Concept Realty Corp. | F90: n_pison@yahoo.com | H90: Fixed | I90: 45061 | J90: MISSING EXPIRY DATE | N90: H S1 506 | O90: H Incomparable Value
A91: Avida Storeys 1 | B91: ACTIVE | C91: P S1 503 | D91: 2-Bedroom | E91: Nino Donato Pison | F91: n_pison@yahoo.com | H91: Fixed | I91: 45184 | J91: MISSING EXPIRY DATE | N91: P S1 503 | O91: P Fantastic 2BR Option for 8 | P91: P S1 503
A92: Avida Storeys 1 | B92: ACTIVE | C92: S S1 717 | D92: 1-Bedroom | E92: Revrose Selyn Pison | F92: n_pison@yahoo.com | H92: Fixed | I92: 45180 | J92: MISSING EXPIRY DATE | N92: S S1 717 | O92: S Urban Dreamscape | P92: S S1 717
A93: Avida Storeys 1 | B93: ACTIVE | C93: S1 408 | D93: STOCKROOM | E93: Edgardo Pison | F93: n_pison@yahoo.com | H93: Fixed | I93: 45180 | J93: MISSING EXPIRY DATE
A94: Avida Storeys 1 | B94: ACTIVE | C94: S2 S1 210 | D94: 1-Bedroom | E94: Dondon Pison | F94: n_pison@yahoo.com | H94: Fixed | I94: 45458 | J94: 46188 | N94: S2 S1 210 | O94: S2 Chic Minimalist Escape | P94: S2 S1 210
A95: Avida Storeys 1 | B95: ACTIVE | C95: Y S1 704 | D95: 2-Bedroom | E95: Goldamier Ybera Chua | F95: goldameirchua@gycmarketingopc.com | H95: Partnership | I95: 45717 | J95: 46082 | N95: Y S1 704 | O95: Y Stylish 2BR Option for up to 6 | P95: Y S1 704
A96: Avida Storeys 2 | B96: ACTIVE | C96: K2 S2 322 | D96: 1-Bedroom | E96: Nathaniel Von Einsiedel | F96: n_pison@yahoo.com | H96: Fixed | I96: 45245 | J96: MISSING EXPIRY DATE | N96: K2 S2 322 | O96: K2 Nordic Haven | P96: K2 S2 322
A97: Avida Storeys 2 | B97: ACTIVE | C97: L S2 716 | D97: 1-Bedroom | E97: Raymund Trenas | F97: raytrenas@gmail.com | H97: Fixed | I97: 45180 | J97: MISSING EXPIRY DATE | N97: L S2 716 | O97: L Iloilo's Quirky Oasis
A98: Avida Storeys 2 | B98: FOR RENEWAL | C98: T2 S2 703 | D98: 1-Bedroom | E98: Leo Paranpan | F98: lparanpan@yahoo.com | G98: 639171273533 | H98: Partnership | I98: 45826 | J98: 46191 | L98: T2 S2 703 - PARANPAN.pdf | N98: T2 S2 703 | O98: T2 Serene Pool View Escape | P98: T2 S2 703
A99: Avida Storeys 2 | B99: ACTIVE | C99: Y2 S2 203 | D99: 1-Bedroom | E99: Ma. Crislyne Mae Espinosa | F99: arlandbarvilla@gmail.com | H99: Partnership | I99: 45506 | J99: 45871 | L99: Y2 S2 203 - ESPINOSA.pdf | N99: Y2 S2 203 | O99: Y2 Pool & Garden Bliss | P99: Y2 S2 203
A100: Bernwood Tower | B100: ACTIVE | C100: BT 1 1222 | D100: Studio | E100: Ruth Santisteban Serrato | F100: ruthserrato@yahoo.com | H100: Partnership | I100: 45748 | J100: 45930 | N100: BT 1 1222 | O100: BT 1 Chic City Studio Retreat | P100: BT 1 1222
...

Sheet Deposit Accounts & Emails
A1: Property | B1: Bank | C1: Account Name | D1: Account Number | E1: Email | F1: Due Date
A2: One Madison Place | B2: Union Bank of the Philippines | C2: One Madison Place Condominium Association | D2: 0012-4003-6593 | E2: onemadisonplace.ao2@fopm.com.ph | F2: Every 15th
A3: Saint Honore & Saint Dominique | B3: Union Bank of the Philippines | C3: SHSD Condominium Association Inc. | D3: 0027-7001-9813 | E3: billing.sthonorestdominique@asia-affinity.com | F3: Every 20th
A4: The Palladium | B4: Union Bank of the Philippines | C4: The Palladium Condominium Association Inc. | D4: 0027-7001-7336 | E4: billing.palladium@asia-affinity.com | F4: Every 20th
A5: WV Towers | B5: BDO Unibank Inc | C5: Westernland Property Development Inc. | D5: 0028-1801-3409 | E5: wvtowers1.2@gmail.com | F5: Every 30th
A6: BA Technology (WiFi) | B6: Gcash | C6: BA Technology | D6: (+63) 994 205 0180 | E6: state unit number in notes | F6: Every 15th
A7: SMDC Style Residences | B7: BDO Unibank Inc | C7: Style Residences Condominium Corporation | D7: 0103-6801-0791 | E7: style.billing@greenmist.ph | F7: Every 30th
A8: One Spatial Iloilo | B8: Eastwest Bank | C8: One Spatial Iloilo Condominium Corp | D8: 2000-3028-7807 | E8: upload to pocket floor app | F8: Every 15th

Sheet Rates
A1: STUDIO
A2: Property | B2: 2 pax | C2: 3 pax | D2: 4 pax | E2: 5 pax
A3: Avida Towers | D3: - | E3: -
D4: - | E4: -
A5: Bernwood Towers
A7: People's Condo | B7: ] | D7: - | E7: -
D8: - | E8: -
A9: St. Honore & St. Dominique | B9: 1999 | C9: 2299 | D9: 2599 | E9: 2899
B10: 2100 | C10: 2400 | D10: 2700 | E10: 3000
A11: Lafayette | B11: 1999 | C11: 2299 | D11: 2599 | E11: 2899
B12: 2100 | C12: 2400 | D12: 2700 | E12: 3000
A15: SMDC STYLE | B15: 1999 | C15: 2299 | D15: 2599 | E15: -
B16: 2100 | C16: 2400 | D16: 2700 | E16: -
A17: One Madison | B17: 1999 | C17: 2299 | D17: 2599
B18: 2100 | C18: 2400 | D18: 2700
A19: The Palladium
A22: 1 BEDROOM
A23: Property | B23: 2 pax | C23: 3 pax | D23: 4 pax | E23: 5 pax | F23: 6 pax
A24: WV Towers | B24: 1800 | C24: =B24+350 -> 2150 | D24: =B24+700 -> 2500
B25: 2050 | C25: =B25+350 -> 2400 | D25: =B25+700 -> 2750
A26: Avida Towers | B26: 1800 | C26: =B26+350 -> 2150 | D26: =B26+700 -> 2500 | E26: =B26+1050 -> 2850 | F26: =B26+1400 -> 3200
B27: 2050 | C27: =B27+350 -> 2400 | D27: =B27+700 -> 2750 | E27: =B27+1050 -> 3100 | F27: =B27+1400 -> 3450
A28: Lafayette | B28: 2600 | C28: =B28+350 -> 2950 | D28: =B28+700 -> 3300 | E28: =B28+1050 -> 3650 | F28: =B28+1400 -> 4000
B29: 2850 | C29: =B29+350 -> 3200 | D29: =B29+700 -> 3550 | E29: =B29+1050 -> 3900 | F29: =B29+1400 -> 4250
A30: The Palladium | B30: 2600 | C30: =B30+350 -> 2950 | D30: =B30+700 -> 3300 | E30: =B30+1050 -> 3650 | F30: =B30+1400 -> 4000
B31: 2850 | C31: =B31+350 -> 3200 | D31: =B31+700 -> 3550 | E31: =B31+1050 -> 3900 | F31: =B31+1400 -> 4250
A32: St. Honore & St. Dominique | B32: 2600 | C32: =B32+350 -> 2950 | D32: =B32+700 -> 3300 | E32: =B32+1050 -> 3650 | F32: =B32+1400 -> 4000
B33: 2850 | C33: =B33+350 -> 3200 | D33: =B33+700 -> 3550 | E33: =B33+1050 -> 3900 | F33: =B33+1400 -> 4250
A35: 2 BEDROOMS
A36: Property | B36: 2 pax | C36: 3 pax | D36: 4 pax | E36: 5 pax | F36: 6 pax | G36: 7 pax | H36: 8 pax
A37: SMDC | B37: 2500 | C37: 2800 | D37: 3100 | E37: 3600 | F37: - | G37: - | H37: -
B38: 2750 | C38: 3050 | D38: 3350 | E38: 3650 | F38: - | G38: - | H38: -
A39: Avida (small) | B39: 2600 | C39: 2600 | D39: 2850 | E39: =D39+350 -> 3200 | F39: =D39+700 -> 3550 | G39: - | H39: -
B40: 2850 | C40: 2850 | D40: 2850 | E40: =D40+350 -> 3200 | F40: =D40+700 -> 3550 | G40: - | H40: -
A41: Avida (big) | B41: 2700 | C41: 2700 | D41: 2700 | E41: =D41+350 -> 3050 | F41: =D41+700 -> 3400 | G41: =D41+1050 -> 3750 | H41: =D41+1400 -> 4100
B42: 2950 | C42: 2950 | D42: 2950 | E42: =D42+350 -> 3300 | F42: =D42+700 -> 3650 | G42: =D42+1050 -> 4000 | H42: =D42+1400 -> 4350
A43: Laffayete | B43: 3500 | C43: 3800 | D43: 4100 | E43: 4400 | F43: 4700 | G43: 5000 | H43: 5300
B44: 3950 | C44: 4250 | D44: 4550 | E44: 4850 | F44: 5150 | G44: 5450 | H44: 5750
A45: Saint H & D | B45: 3000 | C45: 3000 | D45: 3000 | E45: 3350 | F45: =D45+700 -> 3700 | G45: =D45+1050 -> 4050 | H45: =D45+1400 -> 4400
B46: 3250 | C46: 3250 | D46: 3250 | E46: =D46+350 -> 3600 | F46: =D46+700 -> 3950 | G46: =D46+1050 -> 4300 | H46: =D46+1400 -> 4650
A47: One Madison | B47: 3000 | C47: 3000 | D47: 3000 | E47: 3350 | F47: =D47+700 -> 3700 | G47: =D47+1050 -> 4050 | H47: =D47+1400 -> 4400
B48: 3250 | C48: 3250 | D48: 3250 | E48: =D48+350 -> 3600 | F48: =D48+700 -> 3950 | G48: =D48+1050 -> 4300 | H48: =D48+1400 -> 4650

Sheet Extras
B1: Charge | C1: Cost
A2: Extra Person | B2: 300
A4: EARLY CHECK IN
A5: 0.54166667 | B5: 300
A6: 0.58333333 | B6: 250
A7: 0.60416667 | B7: FREE
A8: LATE CHECK OUT
A9: 0.48958333 | B9: FREE
A10: 0.5 | B10: 300
A11: 0.54166667 | B11: 300
A12: 0.58333333 | B12: 500
A14: Day use (8 hours) | B14: 1500
A15: Night use (8 hours) | B15: 1500
B17: Price | C17: Cost
A18: Flat Sheet | B18: 100 | C18: 50
A19: Pillows | B19: 50 | C19: 25
A20: Towels | B20: 50 | C20: 25
A21: Water | B21: 15 | C21: 8
A23: CLEANING FEE (during stay)
B24: Touch up | C24: Linens | D24: General Cleaning
A25: Studio | B25: 200 | C25: 200/set | D25: 350
A26: 1-bedroom | B26: 250 | C26: 200/set | D26: 400
A27: 2-bedroom | B27: 300 | C27: 200/set | D27: 600

Sheet BD Room Aquisitions
A1: UNIT TYPE | B1: DATE SIGNED | C1: STATUS | D1: TERMS | E1: OWNERS NAME | F1: CONTRACTS | G1: COMMISION RELEASED | H1: VOUCHER LINK
A2: OMP T3 10K | B2: 45778 | C2: LIVE | D2: 1 year | E2: Ibrahim Kabeer | F2: OMP T3 10K | G2: PENDING
A3: OMP T1 7U | B3: 45772 | C3: LIVE | D3: 6 months | E3: Milicent Tiu | F3: OMP T1 7U - NOTARY.pdf | G3: RELEASED
A4: SMDC BB 515 | B4: 45767 | C4: LIVE | D4: 6 months | E4: Ariel Sandoy | F4: SMDC BB 515 - NOTARY & S.P.A..pdf | G4: RELEASED
A5: WV T1 1013 | B5: 45767 | C5: LIVE | D5: 6 months | E5: Engr. Rijade Quezon | G5: PENDING
A6: WV T2 611 | B6: 45772 | C6: LIVE | D6: 6 months | E6: Sharmaine Cosculluella Cabial | F6: WV 2 6II.pdf | G6: PENDING
A7: AT T2 209 | B7: 45748 | C7: LIVE | D7: 6 months | E7: Katrina Samoro | G7: PENDING
A8: AT T1 501 | B8: 45753 | C8: LIVE | D8: 1 year | E8: Angelina Cordero | G8: PENDING
A9: SM 9 BC 208 | B9: 45753 | C9: LIVE | D9: 6 months | E9: Dan Mark Jurada | F9: SM 9 BC 208 - JURADA.pdf | G9: RELEASED
A10: SM 10 BA 1420 | B10: 45761 | C10: LIVE | D10: 6 months | E10: Sugar Ganancial | F10: SM 10 BA 1420 - GANANCIAL.pdf | G10: RELEASED
A11: SM 11 BA 624 | B11: 45761 | C11: LIVE | D11: 6 months | E11: Karen Go | F11: SM 11 BB 624 - GO.pdf | G11: RELEASED
A12: SH SW 8C | B12: 45790 | C12: LIVE | D12: 1 year | E12: Maricel Hoy | F12: SD SW 8C CONTRACT - HOY .pdf | G12: RELEASED
A13: TP NW 21B | B13: 45799 | C13: LIVE | D13: 1 year | E13: Amy Lapating | F13: TP NW 21B .pdf | G13: PENDING
A14: LPS 16S | B14: 45800 | C14: LIVE | D14: 1 year | E14: Christine Ladagohon | F14: LPS 16S | G14: PENDING
A15: WV 23 T1 508 | B15: 45799 | C15: PENDING | D15: 1 year | E15: Victor Raymundo Contreras | G15: PENDING
A16: WV 24 T1 511 | B16: 45799 | C16: PENDING | D16: 1 year | E16: Victor Raymundo Contreras | G16: PENDING
A17: WV 25 T1 512 | B17: 45799 | C17: PENDING | D17: 1 year | E17: Victor Raymundo Contreras | G17: PENDING
A18: WV 26 T1 513 | B18: 45799 | C18: PENDING | D18: 1 year | E18: Victor Raymundo Contreras | G18: PENDING
A19: WV 720 | B19: 45799 | C19: PENDING | D19: 1 year | E19: Victor Raymundo Contreras | G19: PENDING
A20: WV 616 | B20: 45799 | C20: PENDING | D20: 1 year | E20: Victor Raymundo Contreras | G20: PENDING
A21: SH NW 5T | B21: 45808 | C21: LIVE | D21: 1 year | E21: Mary Jean Talves Bearneza | F21: SH NW 5T - CONTRACT.pdf | G21: PENDING
A22: TP SW 8D | B22: 45817 | C22: LIVE | D22: 6 months | E22: JOAN REYES | G22: PENDING
A23: LPS 5E | B23: 45809 | C23: LIVE | D23: 1 year | E23: Mary Jean Talves Bearneza | F23: LPS 5E - CONTRACT (1).pdf | G23: PENDING
A24: AT T1 508 | B24: 45811 | C24: PENDING | D24: 1 year | E24: Cherry Pink Villa | G24: PENDING
A25: AT T4 117 | B25: 45811 | C25: LIVE | D25: 1 year | E25: Cherry Pink Villa | G25: PENDING
A26: WV T2 1013 | B26: 45816 | C26: LIVE | D26: 6 months | E26: Rijade Quezon | G26: PENDING
A27: WV T1 921 | B27: 45814 | C27: PENDING | D27: 1 year | E27: Shane Mercolita | G27: PENDING
A28: SMDC BC 117 | B28: 45821 | C28: PENDING | D28: 1 year | E28: Ces Jaranilla Villareal | G28: PENDING
A29: OMP T1 5B | B29: 45824 | C29: PENDING | D29: 1 year | E29: ROSS LIM | G29: PENDING
A30: OMP T2 9L | B30: 45824 | C30: LIVE | D30: 1 year | E30: ROSS LIM | G30: PENDING
A31: SD SW 8A | B31: 45828 | C31: PENDING | D31: 6 months | E31: ELLONAH SVET | G31: PENDING
A32: WV 1 918 | B32: 45828 | C32: PENDING | D32: 6 months | E32: Rose Vargas | G32: PENDING
